Workbook

Sheet Front Sheet
A3: Month | B3: Cars Sold | C3: Total Revenue | D3: Total Gross Profit | E3: Company Expenses | F3: Total SA Gross Profit | G3: Investor Net Profit | H3: Investor Expense | I3: Company Fuel Costs | J3: Other Money In | K3: Other Money Out | L3: Net Profit Exc Investor | M3: Net Exc Investor | N3: Notes
A4: 45839 | B4: 8 | C4: =SUM('Sold Stock'!G3:G10) -> 25546 | D4: ='Sold Stock'!J12 -> 5851.79 | E4: =Expense!E29 -> 386.21 | G4: No Investors | I4: ='Fuel Expense'!D9 -> 247.03 | J4: 0 | K4: 0 | M4: =SUM(L4,J4)-SUM(E4,I4) -> -633.24
A5: 45870 | B5: 6 | C5: =SUM('Sold Stock'!G14:G19) -> 15595 | D5: ='Sold Stock'!J21 -> 464.2 | E5: =Expense!E50 -> 643.31 | G5: No Investors | I5: ='Fuel Expense'!D20 -> 409.74 | J5: 0 | K5: 0 | M5: =SUM(L5,J5)-SUM(E5,I5) -> -1053.05
A6: 45901 | B6: 10 | C6: =SUM('Sold Stock'!G23:G32) -> 35812 | D6: ='Sold Stock'!J34 -> 9866.75 | E6: =Expense!E76 -> 854.31 | G6: No Investors | I6: ='Fuel Expense'!D31 -> 435.01 | J6: 0 | K6: 0 | M6: =SUM(L6,J6)-SUM(E6,I6) -> -1289.32
A7: 45931 | B7: 7 | C7: =SUM('Sold Stock'!G36:G43) -> 26735 | D7: ='Sold Stock'!J45 -> 10118.1 | E7: =Expense!E107 -> 3132.29 | G7: No Investors | I7: ='Fuel Expense'!D39 -> 370.5 | J7: 0 | K7: 0 | M7: =SUM(L7,J7)-SUM(E7,I7) -> -3502.79 | N7: Moved to New Unit
A8: 45962 | B8: 15 | C8: =SUM('Sold Stock'!G47:G58) -> 66552.27 | D8: ='Sold Stock'!J63+Table11[[#This Row],[Other Money In]] -> 19302.64 | E8: =Expense!E140 -> 4356.5 | F8: ='Sold Stock'!L63+Table11[[#This Row],[Other Money In]] -> 11542.482 | G8: =SUM('Sold Stock'!K63) -> 8539.463 | I8: ='Fuel Expense'!D49 -> 422.77 | J8: ='Money in'!D2 -> 200 | K8: ='Money Out'!D4 -> 500 | L8: =Table11[[#This Row],[Total MP Gross Profit]]-SUM(Table11[[#This Row],[Other Money Out]],Table11[[#This Row],[Company Fuel Costs]],Table11[[#This Row],[Investor Expense]],Table11[[#This Row],[Company Expenses]]) -> 6263.212 | M8: =SUM(L8,J8)-SUM(E8,I8) -> 1683.942 | N8: New Office Container Purchased + Upgraded Unit | O8: Obtained Motor Trade Insurance
A9: 45992 | B9: 12 | C9: =SUM('Sold Stock'!G65:G76) -> 71334 | D9: ='Sold Stock'!J78+Table11[[#This Row],[Other Money In]] -> 24070.857 | E9: =Expense!E184 -> 7881.75 | F9: ='Sold Stock'!L78+Table11[[#This Row],[Other Money In]] -> 17194.305 | G9: =SUM('Sold Stock'!K78) -> 6544.542 | I9: ='Fuel Expense'!D57 -> 331.24 | J9: ='Money in'!D10 -> 663.28 | K9: 0 | L9: =Table11[[#This Row],[Total MP Gross Profit]]-SUM(Table11[[#This Row],[Other Money Out]],Table11[[#This Row],[Company Fuel Costs]],Table11[[#This Row],[Investor Expense]],Table11[[#This Row],[Company Expenses]]) -> 8981.3147 | M9: =SUM(L9,J9)-SUM(E9,I9) -> 1431.6047
A10: 46023 | B10: 10 | C10: =SUM('Sold Stock'!G80:G89) -> 70813.28 | D10: ='Sold Stock'!J91+Table11[[#This Row],[Other Money In]] -> 20397.817 | E10: =Expense!E211 -> 6002.86 | F10: ='Sold Stock'!L91+Table11[[#This Row],[Other Money In]] -> 15012.593 | G10: =SUM('Sold Stock'!K91) -> 5945.7433 | H10: ='Investor Car Expense'!D8 -> 370 | I10: ='Fuel Expense'!D72 -> 473.86 | J10: ='Money in'!D15 -> 250 | K10: ='Money Out'!D9 -> 2214.74 | L10: =Table11[[#This Row],[Total MP Gross Profit]]-SUM(Table11[[#This Row],[Other Money Out]],Table11[[#This Row],[Company Fuel Costs]],Table11[[#This Row],[Investor Expense]],Table11[[#This Row],[Company Expenses]]) -> 5951.1333 | M10: =SUM(L10,J10)-SUM(Table11[[#This Row],[Other Money Out]],E10,I10,Table11[[#This Row],[Investor Expense]]) -> -2860.3267 | N10: Upgraded AutoTrader Package To List More Vehicles
A11: 46054 | B11: 10 | C11: =SUM('Sold Stock'!G92:G104) -> 62249.29 | D11: ='Sold Stock'!J104+Table11[[#This Row],[Other Money In]] -> 16553.538 | E11: =Expense!E243 -> 6323.77 | F11: ='Sold Stock'!L104+Table11[[#This Row],[Other Money In]] -> 8941.5089 | G11: =SUM('Sold Stock'!K104) -> 5339.7994 | H11: ='Investor Car Expense'!D25 -> 837.85 | I11: ='Fuel Expense'!D86 -> 564.94 | J11: ='Money in'!D24 -> 1580.95 | K11: 0 | L11: =Table11[[#This Row],[Total MP Gross Profit]]-SUM(Table11[[#This Row],[Other Money Out]],Table11[[#This Row],[Company Fuel Costs]],Table11[[#This Row],[Investor Expense]],Table11[[#This Row],[Company Expenses]]) -> 1214.9489 | M11: =SUM(L11,J11)-SUM(Table11[[#This Row],[Other Money Out]],E11,I11,Table11[[#This Row],[Investor Expense]]) -> -4930.6611 | N11: Accepted Mostly PX Vehicles. Profit Expected In Upcoming Months
A12: 46082 | B12: 16 | C12: =SUM('Sold Stock'!G106:G125) -> 127336.99 | D12: ='Sold Stock'!J122+Table11[[#This Row],[Other Money In]] -> 28777.35 | E12: =Expense!E265 -> 6068.6 | F12: ='Sold Stock'!L122+Table11[[#This Row],[Other Money In]] -> 19683.258 | G12: ='Sold Stock'!K122 -> 9166.072 | H12: ='Investor Car Expense'!D38 -> 673.23 | I12: ='Fuel Expense'!D99 -> 546.41 | J12: ='Money in'!D30 -> 297 | K12: 2000 | L12: =Table11[[#This Row],[Total MP Gross Profit]]-SUM(Table11[[#This Row],[Other Money Out]],Table11[[#This Row],[Company Fuel Costs]],Table11[[#This Row],[Investor Expense]],Table11[[#This Row],[Company Expenses]]) -> 10395.018 | M12: =SUM(L12,J12)-SUM(Table11[[#This Row],[Other Money Out]],E12,I12,Table11[[#This Row],[Investor Expense]]) -> 1403.778
A13: 46113 | B13: 7 | C13: =SUM('Sold Stock'!G124:G139) -> 58311 | D13: ='Sold Stock'!J140+Table11[[#This Row],[Other Money In]] -> 22477.875 | E13: =Expense!E295 -> 2947.86 | F13: ='Sold Stock'!L140+Table11[[#This Row],[Other Money In]] -> 19879.655 | G13: ='Sold Stock'!K140 -> 2598.2198 | H13: ='Investor Car Expense'!D56 -> 58.6 | I13: ='Fuel Expense'!D111 -> 97.79 | J13: ='Money in'!D36 -> 179 | K13: 0 | L13: =Table11[[#This Row],[Total MP Gross Profit]]-SUM(Table11[[#This Row],[Other Money Out]],Table11[[#This Row],[Company Fuel Costs]],Table11[[#This Row],[Investor Expense]],Table11[[#This Row],[Company Expenses]]) -> 16775.405 | M13: =SUM(L13,J13)-SUM(Table11[[#This Row],[Other Money Out]],E13,I13,Table11[[#This Row],[Investor Expense]]) -> 13850.155
A14: 46143
A15: 46174
A16: 46204
A17: 46235
A18: 46266
A19: 46296
A20: TOTAL | B20: =SUM(B4:B19) -> 58 | C20: =SUM(C4:C19) -> 560284.83 | D20: =SUM(D4:D19) -> 157880.92 | E20: =SUM(E4:E19) -> 38597.46 | F20: =SUM(F4:F19) -> 92253.802 | G20: =SUM(G8:G12) -> 35535.62 | H20: =SUM(H4:H19) -> 1939.68 | I20: =SUM(I4:I19) -> 3899.29 | J20: =SUM(J4:J19) -> 3170.23 | K20: =SUM(K4:K19) -> 4714.74 | L20: =SUM(L4:L19) -> 49581.032 | M20: =SUM(M4:M19) -> 4100.0922

Sheet Sold Stock
A2: Month | B2: Date Aquired | C2: Number Plate reference | D2: Make & Model | E2: SA/Investor Name | F2: Total Cost | G2: Sold | H2: Part Ex | I2: SA/Investor Profit Share | J2: Total Profit | K2: Investor Profit | L2: SA Profit | M2: Date Listed | N2: Date Sold | O2: Days to Sell | P2: Platfrom | R2: Invoice Number | S2: Customer Name | T2: Contact info | U2: Warranty | V2: AutoGuard Number
A3: 45839 | B3: 45804 | C3: YD62URJ | D3: Suzuki SX4 | F3: 1684.85 | G3: 2900 | J3: 1215.15 | N3: 45846
A4: 45839 | B4: 45813 | C4: AK09RLY | D4: Golf S | F4: 2165.42 | G4: 2995 | J4: 829.58 | N4: 45865
A5: 45839 | B5: 45815 | C5: GP57PNX | D5: BMW 320i | F5: 2160.74 | G5: 3376 | J5: 1215.26 | N5: 45859
A6: 45839 | B6: 45843 | C6: GJ07OXN | D6: Golf GTI | F6: 1992.81 | G6: 2300 | J6: 307.19 | N6: 45856
A7: 45839 | B7: 45846 | C7: CJ17YNK | D7: Astra Estate | F7: 2736.32 | G7: 2900 | J7: 163.68 | N7: 45846
A8: 45839 | B8: 45847 | C8: EA61BJU | D8: Citroen C1 | F8: 634.46 | G8: 1775 | J8: 1140.54 | N8: 45859
A9: 45839 | B9: 45855 | C9: EO20LVT | D9: Toyota Aygo | F9: 6105.41 | G9: 6400 | J9: 294.59 | N9: 45856
A10: 45839 | B10: 45858 | C10: LS60HBC | D10: Golf Plus | F10: 2214.2 | G10: 2900 | J10: 685.8 | N10: 45858
A11: 45839
A12: 45839 | I12: Total Profit | J12: =SUM(J3:J10) -> 5851.79
A13: 45839
A14: 45870 | B14: 45798 | C14: WR15UXL | D14: Nissan Pulsar | F14: 3108.7 | G14: 1450 | J14: =G14-F14 -> -1658.7 | N14: 45881
A15: 45870 | B15: 45836 | C15: DL68YFF | D15: Astra Turbo SRI | F15: 5151.84 | G15: 5400 | J15: =G15-F15 -> 248.16 | N15: 45894
A16: 45870 | B16: 45846 | C16: KA07DWN | D16: Seat Ibiza | F16: 998.15 | G16: 1295 | J16: =G16-F16 -> 296.85 | N16: 45892
A17: 45870 | B17: 45855 | C17: FL11LXD | D17: Peugeot 207 | F17: 1422.04 | G17: 1900 | J17: =G17-F17 -> 477.96 | N17: -
A18: 45870 | B18: 45862 | C18: EX59VLN | D18: Ford Fiesta | F18: 1359.7 | G18: 2200 | J18: =G18-F18 -> 840.3 | N18: 45901
A19: 45870 | B19: 45864 | C19: YP59MOF | D19: Audi A3 Cabriolet | F19: 3090.37 | G19: 3350 | J19: =G19-F19 -> 259.63 | N19: 45906
A20: 45870
A21: 45870 | I21: Total Profit | J21: =SUM(J14:J19) -> 464.2
A22: 45870
A23: 45901 | B23: 45855 | C23: FL11LXD | D23: Peugeot 207 | F23: 1445.22 | G23: 1900 | J23: =G23-F23 -> 454.78
A24: 45901 | B24: 45861 | C24: LN06ZWP | D24: Ford Focus | F24: 1981.44 | G24: 2195 | J24: =G24-F24 -> 213.56
A25: 45901 | B25: 45864 | C25: YP59MOF | D25: Audi A3 Cabriolet | F25: 3090.37 | G25: 3350 | J25: =G25-F25 -> 259.63
A26: 45901 | B26: 45895 | C26: KF15DGE | D26: BMW 520d | F26: 6168.43 | G26: 7295 | J26: =G26-F26 -> 1126.57
A27: 45901 | B27: 45896 | C27: LD12RHX | D27: Ford Fiesta | F27: 3986.54 | G27: 5895 | J27: =G27-F27 -> 1908.46
A28: 45901 | B28: 45862 | C28: EX59VLN | D28: Ford Fiesta | F28: 1359.7 | G28: 2217 | H28: 343.46 | J28: =G28-F28+Table13[[#This Row],[Part Ex]] -> 1200.76
A29: 45901 | B29: 1st September 2025 | C29: MK11TNN | D29: Skoda Fabia VRS | F29: 1690.46 | G29: 3200 | J29: =G29-F29 -> 1509.54
A30: 45901 | B30: 8th September 2025 | C30: EA56UEC | D30: Ford Focus | F30: 1741.67 | G30: 2295 | J30: =G30-F30 -> 553.33
A31: 45901 | B31: 12th September 2025 | C31: SY09VRT | D31: Volkswagen Polo | F31: 1719.95 | G31: 2900 | J31: =G31-F31 -> 1180.05
A32: 45901 | B32: 19th September 2025 | C32: AE13WEK | D32: Volkswagen Polo | F32: 3104.93 | G32: 4565 | J32: =G32-F32 -> 1460.07
A33: 45901
A34: 45901 | I34: Total Profit | J34: =SUM(J23:J32) -> 9866.75
A35: 45901
A36: 45931 | B36: 45906 | C36: SY13KJZ | D36: Volkswagen Up | F36: 3530.94 | G36: 3995 | J36: =G36-F36 -> 464.06
A37: 45931 | B37: 45916 | C37: LV61VLG | D37: Kia Venga | F37: 2450.67 | G37: 4000 | J37: =G37-F37 -> 1549.33
A38: 45931 | B38: 45915 | C38: YT58ERZ | D38: Smart | F38: 1649.24 | G38: 2600 | J38: =G38-F38 -> 950.76
A39: 45931 | B39: 45922 | C39: YF07NMK | D39: Pegeout 207 | F39: 1051.16 | G39: 2400 | J39: =G39-F39 -> 1348.84
A40: 45931 | B40: 45924 | C40: EO06 TKF | D40: Ford Focus | F40: 910.31 | G40: 1995 | J40: =G40-F40 -> 1084.69
A41: 45931 | B41: 45931 | C41: MT07 NYY | D41: Honda CR-V | F41: 3434.13 | G41: 5995 | J41: =G41-F41 -> 2560.87
A42: 45931 | B42: 45935 | C42: MA58 KUW | D42: Honda Jazz | F42: 1625.91 | G42: 3100 | J42: =G42-F42 -> 1474.09
A43: 45931 | B43: 45950 | C43: MJ62 JKN | D43: Smart | F43: 1964.54 | G43: 2650 | J43: =G43-F43 -> 685.46
A44: 45931
A45: 45931 | I45: Total Profit | J45: =SUM(J36:J43) -> 10118.1
A46: 45931
A47: 45962 | B47: 45860 | C47: BD66AOL | D47: Ford C-Max | E47: Leonardo | F47: ='Stock Data'!K86 -> 6035.87 | G47: 6300 | I47: SA | J47: =G47-F47 -> 264.13 | L47: 264.13 | N47: 45967
A48: 45962 | C48: MM17 XOZ | D48: Nissan Leaf | E48: Jeff | F48: ='Stock Data'!K89 -> 4386.43 | G48: 5394 | I48: 60/40 | J48: =G48-F48 -> 1007.57 | K48: =Table13[[#This Row],[Total Profit]]-Table13[[#This Row],[MP Profit]] -> 403.028 | L48: =Table13[[#This Row],[Total Profit]]*0.6 -> 604.542
A49: 45962 | C49: DV62 OYH | D49: Volkswagen Polo | E49: James | F49: ='Stock Data'!K93 -> 4542.54 | G49: 5795 | I49: 50/50 | J49: =G49-F49 -> 1252.46 | K49: =Table13[[#This Row],[Total Profit]]-Table13[[#This Row],[MP Profit]] -> 626.23 | L49: =Table13[[#This Row],[Total Profit]]*0.5 -> 626.23 | N49: 45966
A50: 45962 | C50: MJ15 EFS | D50: Volkswagen Polo | E50: James | F50: 5243.21 | G50: 6795 | I50: 50/50 | J50: =G50-F50 -> 1551.79 | K50: =Table13[[#This Row],[Total Profit]]-Table13[[#This Row],[MP Profit]] -> 775.895 | L50: =Table13[[#This Row],[Total Profit]]*0.5 -> 775.895 | N50: 45974
A51: 45962 | C51: KU11 GRZ | D51: Skoda Fabia VRS | E51: SA | F51: ='Stock Data'!K88 -> 3149.04 | G51: 3795 | H51: Golf HG57 | I51: SA | J51: =G51-F51 -> 645.96 | L51: =Table13[[#This Row],[Total Profit]] -> 645.96 | N51: 45976
A52: 45962 | C52: HY10 RRO | D52: Nissan Note | E52: SA | F52: ='Stock Data'!K92 -> 2421.85 | G52: 2989.66 | I52: SA | J52: =G52-F52 -> 567.81 | L52: 806.21 | N52: 45980
A53: 45962 | C53: KE65XBC | D53: Seat Ibiza | E53: SA | F53: ='Stock Data'!K85 -> 3651.52 | G53: 3550 | I53: SA | J53: =G53-F53 -> -101.52 | L53: =Table13[[#This Row],[Total Profit]] -> -101.52 | N53: 45980
A54: 45962 | C54: DP64 CXV | D54: Fiat 500 | E54: Jeff | F54: ='Stock Data'!K96 -> 2386.87 | G54: 4695 | I54: 60/40 | J54: =G54-F54 -> 2308.13 | K54: =Table13[[#This Row],[Total Profit]]-Table13[[#This Row],[MP Profit]] -> 923.252 | L54: =Table13[[#This Row],[Total Profit]]*0.6 -> 1384.878 | N54: 45976
A55: 45962 | C55: PK64 LRL | D55: Nissan Juke | E55: Daniel | F55: ='Stock Data'!K91 -> 3516.24 | G55: 5591.61 | I55: 60/40 | J55: =G55-F55 -> 2075.37 | K55: =Table13[[#This Row],[Total Profit]]-Table13[[#This Row],[MP Profit]] -> 830.148 | L55: =Table13[[#This Row],[Total Profit]]*0.6 -> 1245.222 | N55: 45976
A56: 45962 | C56: MK59 FUV | D56: Ford Fiesta | E56: Daniel | F56: ='Stock Data'!K90 -> 3949.35 | G56: 5795 | I56: 60/40 | J56: =G56-F56 -> 1845.65 | K56: =Table13[[#This Row],[Total Profit]]*0.4 -> 738.26 | L56: =Table13[[#This Row],[Total Profit]]*0.6 -> 1107.39 | N56: 45983
A57: 45962 | C57: ET15 BWO | D57: Audi A5 | E57: Joseph | F57: ='Stock Data'!K98 -> 5437.63 | G57: 8602 | I57: 50/50 | J57: =G57-F57 -> 3164.37 | K57: =Table13[[#This Row],[Total Profit]]/2 -> 1582.185 | L57: =1582.185+140.9 -> 1723.085 | N57: 45988
A58: 45962 | C58: EJ11 MYV | D58: Audi A1 | E58: James | F58: ='Stock Data'!K103 -> 5477.23 | G58: 7250 | I58: 50/50 | J58: =G58-F58 -> 1772.77 | K58: =Table13[[#This Row],[Total Profit]]/2 -> 886.385 | L58: =Table13[[#This Row],[Total Profit]]/2 -> 886.385 | N58: 45989
A59: 45962 | C59: YT63 ENJ | D59: Smart | E59: James | F59: ='Stock Data'!K95 -> 2576 | G59: 3900 | I59: 50/50 | J59: =G59-F59 -> 1324 | K59: =Table13[[#This Row],[Total Profit]]/2 -> 662 | L59: =Table13[[#This Row],[Total Profit]]/2 -> 662 | N59: 45990
A60: 45962 | C60: YB15 GRU | D60: Audi A4 | E60: Henry | F60: ='Stock Data'!K111 -> 5975.85 | G60: 7400 | H60: Audi A3 | I60: 50/50 | J60: =G60-F60 -> 1424.15 | K60: 1112.08 | L60: =Table13[[#This Row],[Total Profit]]/2 -> 712.075 | N60: 45991
A61: 45962 | C61: NL55 YXG | D61: Nissan Micra | E61: SA | G61: 500 | H61: 200 | I61: SA | J61: =Table13[[#This Row],[Sold]]-Table13[[#This Row],[Part Ex]] -> 300 | L61: 300 | N61: 45991
A62: 45962
A63: 45962 | I63: Total Profit | J63: =SUM(J47:J60) -> 19102.64 | K63: =SUM(K47:K60) -> 8539.463 | L63: =SUM(L47:L60) -> 11342.482
A64: 45962
A65: 45992 | C65: EA65NDL | D65: Ford Fiesta | E65: James | F65: ='Stock Data'!K120 -> 3556.61 | G65: 3815 | I65: 60/40 | J65: =G65-F65 -> 258.39 | K65: =Table13[[#This Row],[Total Profit]]*0.4 -> 103.356 | L65: =Table13[[#This Row],[Total Profit]]*0.6 -> 155.034 | O65: Cargurus
A66: 45992 | C66: LR15 EUT | D66: Golf Match | E66: James | F66: ='Stock Data'!K129 -> 5248.4033 | G66: 7495 | I66: 50/50 | J66: =G66-F66 -> 2246.5967 | K66: =Table13[[#This Row],[Total Profit]]/2 -> 1123.2983 | L66: =Table13[[#This Row],[Total Profit]]/2 -> 1123.2983 | O66: Autotrader
A67: 45992 | C67: CX14PVO | D67: Fiat 500 | E67: Leonardo | F67: ='Stock Data'!K122 -> 4818.1433 | G67: 5995 | I67: 60/40 | J67: =Table13[[#This Row],[Sold]]-Table13[[#This Row],[Total Cost]] -> 1176.8567 | K67: =Table13[[#This Row],[Total Profit]]*0.4-12 -> 458.74267 | L67: =Table13[[#This Row],[Total Profit]]*0.6 -> 706.114 | O67: Autotrader
A68: 45992 | C68: NU65 EDH | D68: Mazda 6 | E68: Joseph | F68: ='Stock Data'!K132 -> 4399.21 | G68: 7250 | I68: 50/50 | J68: =G68-F68 -> 2850.79 | K68: =Table13[[#This Row],[Total Profit]]/2 -> 1425.395 | L68: =Table13[[#This Row],[Total Profit]]/2 -> 1425.395 | O68: Autotrader
A69: 45992 | C69: HG08 EPZ | D69: Audi A3 | E69: SA | F69: ='Stock Data'!J123 -> 8 | G69: 1995 | I69: SA | J69: =G69-F69 -> 1987 | L69: =Table13[[#This Row],[Total Profit]]-400.01 -> 1586.99 | O69: Autotrader
A70: 45992 | C70: LM64 FWU | D70: Fiat 500 Conv | E70: SA | F70: ='Stock Data'!K144 -> 3730.74 | G70: 5400 | I70: SA | J70: =G70-F70 -> 1669.26 | L70: =Table13[[#This Row],[Total Profit]] -> 1669.26 | O70: Walk-in
A71: 45992 | C71: LN11 ZC | D71: Peugeot 107 | E71: SA | F71: ='Stock Data'!K113 -> 2571.2167 | G71: ='Stock Data'!L113 -> 3500 | I71: SA | J71: =G71-F71 -> 928.78333 | L71: =Table13[[#This Row],[Sold]]-Table13[[#This Row],[Total Cost]] -> 928.78333 | N71: 20/12/2025 | O71: Cargurus
A72: 45992 | C72: CV65VMZ | D72: Polo GT | E72: Joseph | F72: ='Stock Data'!K141 -> 4528.8 | G72: ='Stock Data'!L141 -> 6595 | I72: 50/50 | J72: =G72-F72 -> 2066.2 | K72: =Table13[[#This Row],[Total Profit]]/2 -> 1033.1 | L72: =Table13[[#This Row],[Total Profit]]/2 -> 1033.1
A73: 45992 | C73: JFZ1824 | D73: Polo Auto | E73: James | F73: ='Stock Data'!K125 -> 4895.8 | G73: ='Stock Data'!L125 -> 7295 | I73: 50/50 | J73: =G73-F73 -> 2399.2 | K73: =Table13[[#This Row],[Total Profit]]/2 -> 1199.6 | L73: =Table13[[#This Row],[Total Profit]]/2+80 -> 1279.6
A74: 45992 | C74: SX14KKH | D74: BMW 320i | E74: Daniel | F74: ='Stock Data'!K139 -> 6647.9 | G74: ='Stock Data'!L139 -> 9050 | I74: 50/50 | J74: =G74-F74 -> 2402.1 | K74: =Table13[[#This Row],[Total Profit]]/2 -> 1201.05 | L74: =Table13[[#This Row],[Total Profit]]/2 -> 1201.05 | N74: 27/12/2025 | O74: Autotrader
A75: 45992 | C75: WD63NXU | D75: Nissan Navara | E75: SA | F75: ='Stock Data'!K119 -> 6737.99 | G75: ='Stock Data'!L119 -> 9994 | I75: SA | J75: =G75-F75 -> 3256.01 | L75: =Table13[[#This Row],[Total Profit]] -> 3256.01 | N75: 30/12/2025 | O75: Autotrader
A76: 45992 | C76: HG57 MDE | D76: Volkswagen Polo | E76: SA | F76: ='Stock Data'!J124 -> 783.61 | G76: 2950 | I76: SA | J76: =G76-F76 -> 2166.39 | L76: =Table13[[#This Row],[Total Profit]] -> 2166.39
A77: 45992
A78: 45992 | I78: Total Profit | J78: =SUM(J65:J76) -> 23407.577 | K78: =SUM(K65:K76) -> 6544.542 | L78: =SUM(L65:L76) -> 16531.025
A79: 45992
A80: 46023 | C80: VX15 DYU | D80: Ford Kuga | E80: Daniel | F80: ='Stock Data'!K156 -> 5602.5433 | G80: 7793.28 | I80: 50/50 | J80: =Table13[[#This Row],[Sold]]-Table13[[#This Row],[Total Cost]] -> 2190.7367 | K80: =Table13[[#This Row],[Total Profit]]/2-100 -> 995.36833 | L80: =Table13[[#This Row],[Total Profit]]/2+100 -> 1195.3683
A81: 46023 | C81: SV63 KKO | D81: BMW 5 Series | E81: Joseph | F81: ='Stock Data'!K160 -> 6270.68 | G81: 8400 | I81: 50/50 | J81: =G81-F81 -> 2129.32 | K81: =Table13[[#This Row],[Total Profit]]/2-100 -> 964.66 | L81: =Table13[[#This Row],[Total Profit]]/2+'BMW GT SV63 KKO'!H6+100 -> 1664.3 | N81: 46036
A82: 46023 | C82: SP08 KLX | D82: Audi S5 | E82: James | F82: ='Stock Data'!K155 -> 5494.46 | G82: 8995 | I82: 50/50 | J82: =G82-F82 -> 3500.54 | K82: =Table13[[#This Row],[Total Profit]]/2-100 -> 1650.27 | L82: =Table13[[#This Row],[Total Profit]]/2+100 -> 1850.27 | N82: 46038
A83: 46023 | C83: WM63 XCE | D83: Fiat 500 | E83: SA | F83: ='Stock Data'!K157 -> 2639.28 | G83: 3595 | I83: SA | J83: =G83-F83 -> 955.72 | L83: =Table13[[#This Row],[Total Profit]] -> 955.72 | N83: 46038
A84: 46023 | C84: EJ14UZC | D84: BMW 520D | E84: SA | F84: ='Stock Data'!K166 -> 6541.12 | G84: 8495 | I84: SA | J84: =G84-F84 -> 1953.88 | L84: =Table13[[#This Row],[Total Profit]] -> 1953.88 | N84: 46039
A85: 46023 | C85: SR16 HKT | D85: Smart Premium | E85: SA | F85: ='Stock Data'!K170 -> 5253.02 | G85: ='Stock Data'!L170 -> 8995 | I85: SA | J85: =G85-F85 -> 3741.98 | L85: =Table13[[#This Row],[Total Profit]] -> 3741.98 | N85: 46045
A86: 46023 | B86: 45975 | C86: MF12 NKN | D86: Audi A1 | E86: Joseph | F86: ='Stock Data'!K152 -> 4390.79 | G86: 7250 | I86: 50/50 | J86: =G86-F86 -> 2859.21 | K86: =Table13[[#This Row],[Total Profit]]/2-100 -> 1329.605 | L86: =Table13[[#This Row],[Total Profit]]/2+ 60.88+100 -> 1590.485 | N86: 46047
A87: 46023 | B87: 45965 | C87: KM17 YTV | D87: Nissan Qashqai | E87: SA | F87: ='Stock Data'!K150 -> 8361.51 | G87: 8295 | H87: 1500 | I87: SA | J87: =G87-F87 -> -66.51 | L87: =Table13[[#This Row],[Total Profit]] -> -66.51 | N87: 46050
A88: 46023 | B88: 46050 | C88: EU14 NOW | D88: Peugeot 2008 | E88: SA | F88: ='Stock Data'!K173 -> 1328.74 | G88: 2000 | I88: SA | J88: =G88-F88 -> 671.26 | L88: =Table13[[#This Row],[Total Profit]] -> 671.26 | N88: 46053
A89: 46023 | B89: 45983 | C89: CE65 MJJ | D89: Polo BlueGT | E89: Daniel | F89: ='Stock Data'!K149 -> 4783.32 | G89: 6995 | I89: 50/50 | J89: =G89-F89 -> 2211.68 | K89: =Table13[[#This Row],[Total Profit]]/2-100 -> 1005.84 | L89: =Table13[[#This Row],[Total Profit]]/2+100 -> 1205.84
A90: 46023
A91: 46023 | I91: Total Profit | J91: =SUM(J80:J89) -> 20147.817 | K91: =SUM(K80:K89) -> 5945.7433 | L91: =SUM(L80:L89) -> 14762.593
A92: 46023
A93: 46054 | B93: 46031 | C93: GY14BZC | D93: Octavia VRS | E93: SA | F93: ='Stock Data'!K186 -> 8246.15 | G93: 6500 | H93: 4000 | I93: SA | J93: =G93-F93 -> -1746.15 | L93: =Table13[[#This Row],[Total Profit]] -> -1746.15 | N93: 46054
A94: 46054 | B94: 45989 | C94: KU13 FBF | D94: Honda CRV | E94: James | F94: ='Stock Data'!K176 -> 5732.32 | G94: 7995 | I94: 50/50 | J94: =G94-F94 -> 2262.68 | K94: =Table13[[#This Row],[Total Profit]]/2-100 -> 1031.34 | L94: =Table13[[#This Row],[Total Profit]]/2+99+120+100 -> 1450.34 | N94: 46055
A95: 46054 | B95: 46000 | C95: RV62 UMD | D95: Nissan Note | E95: Leonardo | F95: ='Stock Data'!K181 -> 2850.71 | G95: 5375 | I95: 70/30 | J95: =G95-F95 -> 2524.29 | K95: =Table13[[#This Row],[Total Profit]]*0.3 -> 757.287 | L95: =Table13[[#This Row],[Total Profit]]-Table13[[#This Row],[Investor Profit]] -> 1767.003 | N95: 46060
A96: 46054 | B96: 46057 | C96: MF15 OPJ | D96: Peugeot 3008 | E96: Jeff | F96: ='Stock Data'!K196 -> 4187.38 | G96: ='Stock Data'!L196 -> 6394.29 | I96: 70/30 | J96: =G96-F96 -> 2206.91 | K96: =Table13[[#This Row],[Total Profit]]*0.3 -> 662.073 | L96: =Table13[[#This Row],[Total Profit]]-Table13[[#This Row],[Investor Profit]] -> 1544.837 | N96: 46065
A97: 46054 | B97: 46057 | C97: EN63 TKA | D97: Audi A1 | E97: James | F97: ='Stock Data'!K195+120 -> 7792.2 | G97: 9795 | I97: 65/35 | J97: =G97-F97 -> 2002.8 | K97: =Table13[[#This Row],[Total Profit]]*0.35 -> 700.98 | L97: =(6995-Table13[[#This Row],[Total Cost]])*0.65-Table13[[#This Row],[Investor Profit]] -> -1219.16
A98: 46054 | B98: 46060 | C98: YY65 CAU | D98: V Corsa | E98: Daniel | F98: ='Stock Data'!K200 -> 5238.035 | G98: 6995 | I98: 65/35 | J98: =G98-F98 -> 1756.965 | K98: =Table13[[#This Row],[Total Profit]]*0.35 -> 614.93775 | L98: =Table13[[#This Row],[Total Profit]]-Table13[[#This Row],[Investor Profit]] -> 1142.0273
A99: 46054 | B99: 45975 | C99: YB65 XPP | D99: Fiat 500 | E99: Jeff | F99: ='Stock Data'!K179 -> 4279.18 | G99: 5400 | I99: 50/50 | J99: =G99-F99 -> 1120.82 | K99: =Table13[[#This Row],[Total Profit]]/2-100 -> 460.41 | L99: =Table13[[#This Row],[Total Profit]]/2+100 -> 660.41
A100: 46054 | B100: 45985 | C100: OY61 UTH | D100: Jaguar XF | E100: Jeff | F100: ='Stock Data'!K178 -> 3526.9367 | G100: 5000 | I100: 50/50 | J100: =G100-F100 -> 1473.0633 | K100: =Table13[[#This Row],[Total Profit]]/2-100 -> 636.53167 | L100: =Table13[[#This Row],[Total Profit]]/2+100+(180-83.74) -> 932.79167
A101: 46054 | B101: 45993 | C101: CY64 ACO | D101: Polo | E101: Jeff | F101: ='Stock Data'!K180 -> 4642.52 | G101: 5795 | I101: 50/50 | J101: =G101-F101 -> 1152.48 | K101: =Table13[[#This Row],[Total Profit]]/2-100 -> 476.24 | L101: =Table13[[#This Row],[Total Profit]]/2+100 -> 676.24
...

Sheet Stock Data
B2: Month | C2: Date Aquired | D2: Plate Number | E2: Make & Model | F2: Investor/SA | G2: Source | H2: PX Value | I2: Price | J2: Reconditioning costs | K2: Total Cost | L2: Sold | M2: Profit | N2: Status
B3: 45839 | C3: 45798 | D3: WR15UXL | G3: Copart | I3: 2360 | J3: 748.7 | K3: =SUM(I3:J3) -> 3108.7 | L3: - | M3: - | N3: Need to put on copart
B4: 45839 | C4: 45804 | D4: YD62URJ | E4: Suzuki SX4 | G4: Copart | I4: 955.36 | J4: 729.49 | K4: =SUM(I4:J4) -> 1684.85 | L4: 2900 | M4: =L4-SUM(I4:J4) -> 1215.15 | N4: Sold
B5: 45839 | C5: 45807 | D5: WD63NXU | E5: Nissan Navara | G5: FB | I5: 2000 | J5: 4597.14 | K5: =SUM(I5:J5) -> 6597.14 | L5: - | M5: - | N5: Charlie fixing fuel pump
B6: 45839 | C6: 45813 | D6: AK09RLY | E6: Golf S | G6: FB | I6: 1250 | J6: 915.42 | K6: =SUM(I6:J6) -> 2165.42 | L6: 2995 | M6: =L6-SUM(I6:J6) -> 829.58 | N6: Sold
B7: 45839 | C7: 45815 | D7: GP57PNX | E7: BMW 320i | G7: FB | I7: 1750 | J7: 410.74 | K7: =SUM(I7:J7) -> 2160.74 | L7: 3376 | M7: =L7-SUM(I7:J7) -> 1215.26 | N7: Sold
B8: 45839 | C8: 45836 | D8: DL68YFF | E8: Astra Turbo SRI | G8: FB | I8: 2999 | J8: 2152.84 | K8: =SUM(I8:J8) -> 5151.84 | L8: - | M8: - | N8: On Sale
B9: 45839 | C9: 45843 | D9: GJ07OXN | E9: Golf GTI | G9: PX Swap | I9: 1976.81 | J9: 16 | K9: =SUM(I9:J9) -> 1992.81 | L9: 2300 | M9: =L9-SUM(I9:J9) -> 307.19 | N9: Sold
B10: 45839 | C10: 45846 | D10: KA07DWN | E10: Seat Ibiza | G10: FB | I10: 450 | J10: 538.14 | K10: =SUM(I10:J10) -> 988.14 | L10: - | M10: - | N10: On Sale
B11: 45839 | C11: 45846 | D11: CJ17YNK | E11: Astra Estate | G11: Private | I11: 2700 | J11: 36.32 | K11: =SUM(I11:J11) -> 2736.32 | L11: 2900 | M11: =L11-SUM(I11:J11) -> 163.68 | N11: Sold
B12: 45839 | C12: 45847 | D12: EA61BJU | E12: Citroen C1 | G12: FB | I12: 500 | J12: 134.46 | K12: =SUM(I12:J12) -> 634.46 | L12: 1775 | M12: =L12-SUM(I12:J12) -> 1140.54 | N12: Sold
B13: 45839 | C13: 45855 | D13: FL11LXD | E13: Peugeot 207 | G13: FB | I13: 750 | J13: 695.22 | K13: =SUM(I13:J13) -> 1445.22 | L13: - | M13: - | N13: Need To Change Boot Lock
B14: 45839 | C14: 45855 | D14: EO20LVT | E14: Toyota Aygo | G14: Copart | I14: 6030.41 | J14: 75 | K14: =SUM(I14:J14) -> 6105.41 | L14: 6400 | M14: =L14-SUM(I14:J14) -> 294.59 | N14: Sold
B15: 45839 | C15: 45858 | D15: LS60HBC | E15: Golf Plus | G15: FB | I15: 2200 | J15: 14.2 | K15: =SUM(I15:J15) -> 2214.2 | L15: 2900 | M15: =L15-SUM(I15:J15) -> 685.8 | N15: Sold
B16: 45839 | C16: 45859 | D16: KE65XBC | E16: Seat Ibiza | G16: FB | I16: 1200 | J16: 2451.52 | K16: =SUM(I16:J16) -> 3651.52 | L16: - | M16: - | N16: Being prepared
B17: 45839 | C17: 45860 | D17: BD66AOL | E17: Ford C-Max | G17: FB | I17: 4387.08 | J17: 1648.79 | K17: =SUM(I17:J17) -> 6035.87 | L17: - | M17: - | N17: Need to get tyres sorted + Clean, Photos and List
B18: 45839 | C18: 45861 | D18: LN06ZWP | E18: Ford Focus | G18: FB | I18: 500 | J18: 1481.44 | K18: =SUM(I18:J18) -> 1981.44 | L18: - | M18: - | N18: Being prepared
B19: 45839 | C19: 45862 | D19: EX59VLN | E19: Ford Fiesta | G19: FB | I19: 1200 | J19: 159.7 | K19: =SUM(I19:J19) -> 1359.7 | L19: - | M19: - | N19: On Sale
B20: 45839 | C20: 45864 | D20: YP59MOF | E20: Audi A3 Conv | G20: FB | I20: 800 | J20: 2290.37 | K20: =SUM(I20:J20) -> 3090.37 | L20: - | M20: - | N20: Need to wash and install third break lights
B21: 45839
B22: 45870 | C22: 45798 | D22: WR15UXL | E22: Nissan Pulsar | G22: Copart | I22: 2360 | J22: 748.7 | K22: =SUM(I22:J22) -> 3108.7 | L22: 1450 | M22: =L22-SUM(I22:J22) -> -1658.7 | N22: Sold
B23: 45870 | C23: 45807 | D23: WD63NXU | E23: Nissan Navara | G23: FB | I23: 2000 | J23: 890.5 | K23: =SUM(I23:J23) -> 2890.5 | L23: - | M23: - | N23: Recovering when focus is done
B24: 45870 | C24: 45836 | D24: DL68YFF | E24: Astra Turbo SRI | G24: FB | I24: 2999 | J24: 2152.84 | K24: =SUM(I24:J24) -> 5151.84 | L24: 5400 | M24: =L24-SUM(I24:J24) -> 248.16 | N24: Sold
B25: 45870 | C25: 45846 | D25: KA07DWN | E25: Seat Ibiza | G25: FB | I25: 450 | J25: 548.15 | K25: =SUM(I25:J25) -> 998.15 | L25: 1295 | M25: =L25-SUM(I25:J25) -> 296.85 | N25: Sold
B26: 45870 | C26: 45855 | D26: FL11LXD | E26: Peugeot 207 | G26: FB | I26: 750 | J26: 672.04 | K26: =SUM(I26:J26) -> 1422.04 | L26: 1900 | M26: =L26-SUM(I26:J26) -> 477.96 | N26: Sold
B27: 45870 | C27: 45859 | D27: KE65XBC | E27: Seat Ibiza | G27: FB | I27: 1200 | J27: 1867.96 | K27: =SUM(I27:J27) -> 3067.96 | L27: - | M27: - | N27: Body Shop
B28: 45870 | C28: 45860 | D28: BD66AOL | E28: Ford C-Max | G28: FB | I28: 4387.08 | J28: 1527.85 | K28: =SUM(I28:J28) -> 5914.93 | L28: - | M28: - | N28: On Sale
B29: 45870 | C29: 45861 | D29: LN06ZWP | E29: Ford Focus | G29: FB | I29: 500 | J29: 1251.87 | K29: =SUM(I29:J29) -> 1751.87 | L29: - | M29: - | N29: On Sale
B30: 45870 | C30: 45862 | D30: EX59VLN | E30: Ford Fiesta | G30: FB | I30: 1200 | J30: 159.7 | K30: =SUM(I30:J30) -> 1359.7 | L30: 2200 | M30: =L30-SUM(I30:J30) -> 840.3 | N30: Sold
B31: 45870 | C31: 45864 | D31: YP59MOF | E31: Audi A3 Cabriolet | G31: FB | I31: 800 | J31: 2290.37 | K31: =SUM(I31:J31) -> 3090.37 | L31: 3350 | M31: =L31-SUM(I31:J31) -> 259.63 | N31: Sold
B32: 45870 | C32: 45873 | D32: EA65NDL | E32: Ford Fiesta | G32: FB | I32: 2250 | J32: 1157.12 | K32: =SUM(I32:J32) -> 3407.12 | L32: - | M32: - | N32: On Sale
B33: 45870 | C33: 45895 | D33: KF15DGE | E33: BMW 520d | G33: Carwow | I33: 4900 | K33: =SUM(I33:J33) -> 4900 | L33: - | M33: -
B34: 45870 | C34: 45896 | D34: LD12RHX | E34: Ford Fiesta | G34: Carwow | I34: 3769 | K34: =SUM(I34:J34) -> 3769 | L34: - | M34: -
B35: 45870 | C35: 45900 | D35: KP53AUR | E35: Mercedes A Class | G35: Part Ex | K35: =SUM(I35:J35) -> 0 | M35: =L35-SUM(I35:J35) -> 0
B36: 45870
B37: 45901 | C37: 45807 | D37: WD63NXU | E37: Nissan Navara | G37: FB | I37: 2000 | J37: 4597.14 | K37: =SUM(I37:J37) -> 6597.14 | N37: Recovering when focus is done
B38: 45901 | C38: 45859 | D38: KE65XBC | E38: Seat Ibiza | G38: FB | I38: 1200 | J38: 2451.52 | K38: =SUM(I38:J38) -> 3651.52 | N38: need to fix and list
B39: 45901 | C39: 45855 | D39: FL11LXD | E39: Peugeot 207 | G39: FB | I39: 750 | J39: 695.22 | K39: =SUM(I39:J39) -> 1445.22 | L39: 1900 | M39: =L39-SUM(I39:J39) -> 454.78 | N39: Sold
B40: 45901 | C40: 45860 | D40: BD66AOL | E40: Ford C-Max | G40: FB | I40: 4387.08 | J40: 1648.79 | K40: =SUM(I40:J40) -> 6035.87 | N40: On Sale
B41: 45901 | C41: 45861 | D41: LN06ZWP | E41: Ford Focus | G41: FB | I41: 500 | J41: 1481.44 | K41: =SUM(I41:J41) -> 1981.44 | L41: 2195 | M41: =L41-SUM(I41:J41) -> 213.56 | N41: Sold
B42: 45901 | C42: 45864 | D42: YP59MOF | E42: Audi A3 Cabriolet | G42: FB | I42: 800 | J42: 2290.37 | K42: =SUM(I42:J42) -> 3090.37 | L42: 3350 | M42: =L42-SUM(I42:J42) -> 259.63 | N42: Sold
B43: 45901 | C43: 45873 | D43: EA65NDL | E43: Ford Fiesta | G43: FB | I43: 2250 | J43: 1172.08 | K43: =SUM(I43:J43) -> 3422.08 | N43: On Sale
B44: 45901 | C44: 45895 | D44: KF15DGE | E44: BMW 520d | G44: Carwow | I44: 4900 | J44: 1268.43 | K44: =SUM(I44:J44) -> 6168.43 | L44: 7295 | M44: =L44-SUM(I44:J44) -> 1126.57 | N44: Sold
B45: 45901 | C45: 45896 | D45: LD12RHX | E45: Ford Fiesta | G45: Carwow | I45: 3769 | J45: 217.54 | K45: =SUM(I45:J45) -> 3986.54 | L45: 5895 | M45: =L45-SUM(I45:J45) -> 1908.46 | N45: Sold
B46: 45901 | C46: 45862 | D46: EX59VLN | E46: Ford Fiesta | G46: FB | I46: 1200 | J46: 159.7 | K46: =SUM(I46:J46) -> 1359.7 | L46: 2217 | M46: =L46-SUM(I46:J46) -> 857.3 | N46: Sold
B47: 45901 | C47: 45900 | D47: KP53AUR | E47: Mercedes A Class | G47: Part Ex | J47: 6.54 | K47: =SUM(I47:J47) -> 6.54 | L47: 350 | M47: =L47-SUM(I47:J47) -> 343.46 | N47: Waiting for land lord to return
B48: 45901 | C48: 1st September 2025 | D48: MK11TNN | E48: Skoda Fabia VRS | G48: Private | I48: 1400 | J48: 290.46 | K48: =SUM(I48:J48) -> 1690.46 | L48: 3200 | M48: =L48-SUM(I48:J48) -> 1509.54 | N48: Sold
B49: 45901 | C49: 8th September 2025 | D49: EA56UEC | E49: Ford Focus | G49: Carwow | I49: 1175 | J49: 566.67 | K49: =SUM(I49:J49) -> 1741.67 | L49: 2295 | M49: =L49-SUM(I49:J49) -> 553.33 | N49: Sold
B50: 45901 | C50: 6th september 2025 | D50: SY13KJZ | E50: Volkswagen Up | G50: Facebook | I50: 2500 | J50: 1030.94 | K50: =SUM(I50:J50) -> 3530.94 | N50: On Sale
B51: 45901 | C51: 12th September 2025 | D51: SY09VRT | E51: Volkswagen Polo | G51: Facebook | I51: 1190 | J51: 529.95 | K51: =SUM(I51:J51) -> 1719.95 | L51: 2900 | M51: =L51-SUM(I51:J51) -> 1180.05 | N51: Sold
B52: 45901 | C52: 16th September 2025 | D52: LV61VLG | E52: Kia Venga | G52: Carwow | I52: 2174.8 | K52: =SUM(I52:J52) -> 2174.8 | N52: On Sale
B53: 45901 | C53: 19th September 2025 | D53: AE13WEK | E53: Volkswagen Polo | G53: Carwow | I53: 3072.8 | J53: 32.13 | K53: =SUM(I53:J53) -> 3104.93 | L53: 4565 | M53: =L53-SUM(I53:J53) -> 1460.07 | N53: Sold
B54: 45901 | C54: 15th September 2025 | D54: YT58ERZ | E54: Smart | G54: CarWow | I54: 925 | J54: 485.44 | K54: =SUM(I54:J54) -> 1410.44 | N54: On Sale
B55: 45901 | C55: 22nd September 2025 | D55: YF07NMK | E55: Pegeout 207 | G55: Facebook | I55: 325 | J55: 726.16 | K55: =SUM(I55:J55) -> 1051.16 | N55: On Sale
B56: 45901 | C56: 24th September 2025 | D56: EO06 TKF | E56: Ford Focus | G56: Carwow | I56: 725 | J56: 185.31 | K56: =SUM(I56:J56) -> 910.31 | N56: On Sale
B57: 45901 | C57: 28th September 2025 | D57: KU11 GRZ | E57: Skoda Fabia VRS | G57: Carwow | I57: 2100 | J57: 1049.04 | K57: =SUM(I57:J57) -> 3149.04
B58: 45901 | C58: 29th September 2025 | D58: MM17 XOZ | E58: Nissan Leaf | G58: Carwow | I58: 3400 | J58: 966.43 | K58: =SUM(I58:J58) -> 4366.43
B59: 45901
B60: 45931 | C60: 45807 | D60: WD63NXU | E60: Nissan Navara | G60: FB | I60: 2000 | J60: 4597.14 | K60: =SUM(I60:J60) -> 6597.14 | N60: Recovering when focus is done
B61: 45931 | C61: 45859 | D61: KE65XBC | E61: Seat Ibiza | G61: FB | I61: 1200 | J61: 2451.52 | K61: =SUM(I61:J61) -> 3651.52 | N61: On Sale
B62: 45931 | C62: 45860 | D62: BD66AOL | E62: Ford C-Max | G62: FB | I62: 4387.08 | J62: 1648.79 | K62: =SUM(I62:J62) -> 6035.87 | N62: On Sale
B63: 45931 | C63: 45873 | D63: EA65NDL | E63: Ford Fiesta | G63: FB | I63: 2250 | J63: 1172.08 | K63: =SUM(I63:J63) -> 3422.08 | N63: On Sale
B64: 45931 | C64: 45906 | D64: SY13KJZ | E64: Volkswagen Up | G64: FB | I64: 2500 | J64: 1030.94 | K64: =SUM(I64:J64) -> 3530.94 | L64: 3995 | M64: =L64-SUM(I64:J64) -> 464.06 | N64: Sold
B65: 45931 | C65: 45916 | D65: LV61VLG | E65: Kia Venga | G65: FB | I65: 1900 | J65: 550.67 | K65: =SUM(I65:J65) -> 2450.67 | L65: 4000 | M65: =L65-SUM(I65:J65) -> 1549.33 | N65: Sold
B66: 45931 | C66: 45915 | D66: YT58ERZ | E66: Smart | G66: FB | I66: 925 | J66: 724.24 | K66: =SUM(I66:J66) -> 1649.24 | L66: 2600 | M66: =L66-SUM(I66:J66) -> 950.76 | N66: Sold
B67: 45931 | C67: 45922 | D67: YF07NMK | E67: Pegeout 207 | G67: Carwow | I67: 325 | J67: 726.16 | K67: =SUM(I67:J67) -> 1051.16 | L67: 2400 | M67: =L67-SUM(I67:J67) -> 1348.84 | N67: Sold
B68: 45931 | C68: 45924 | D68: EO06 TKF | E68: Ford Focus | G68: Carwow | I68: 725 | J68: 185.31 | K68: =SUM(I68:J68) -> 910.31 | L68: 1995 | M68: =L68-SUM(I68:J68) -> 1084.69 | N68: Sold
B69: 45931 | C69: 45928 | D69: KU11 GRZ | E69: Skoda Fabia VRS | G69: FB | I69: 2100 | J69: 1049.04 | K69: =SUM(I69:J69) -> 3149.04 | N69: On Sale
B70: 45931 | C70: 45929 | D70: MM17 XOZ | E70: Nissan Leaf | G70: Part Ex | I70: 3400 | J70: 966.43 | K70: =SUM(I70:J70) -> 4366.43 | N70: On Sale
B71: 45931 | C71: 45931 | D71: MK59 FUV | E71: Ford Fiesta | G71: Private | I71: 3100 | J71: 426.9 | K71: =SUM(I71:J71) -> 3526.9 | N71: On Sale
B72: 45931 | C72: 45931 | D72: MT07 NYY | E72: Honda CR-V | G72: Carwow | I72: 2800 | J72: 634.13 | K72: =SUM(I72:J72) -> 3434.13 | L72: 5995 | M72: =L72-SUM(I72:J72) -> 2560.87 | N72: Sold
B73: 45931 | C73: 45935 | D73: MA58 KUW | E73: Honda Jazz | G73: Yard | I73: 1000 | J73: 625.91 | K73: =SUM(I73:J73) -> 1625.91 | L73: 3100 | M73: =L73-SUM(I73:J73) -> 1474.09 | N73: Sold
B74: 45931 | C74: 45935 | D74: PK64 LRL | E74: Nissan Juke | G74: Facebook | I74: 1500 | J74: 2016.24 | K74: =SUM(I74:J74) -> 3516.24 | N74: On Sale
B75: 45931 | C75: 45947 | D75: HY10 RRO | E75: Nissan Note | G75: Carwow | I75: 1400 | J75: 783.05 | K75: =SUM(I75:J75) -> 2183.05 | N75: On Sale
B76: 45931 | C76: 45946 | D76: DV62 OYH | E76: Volkswagen Polo | G76: Carwow | I76: 3800 | J76: 742.54 | K76: =SUM(I76:J76) -> 4542.54 | N76: On Sale
B77: 45931 | C77: 45950 | D77: MJ15 EFS | E77: Volkswagen Polo | G77: Carwow | I77: 4400 | J77: 843.21 | K77: =SUM(I77:J77) -> 5243.21
B78: 45931 | C78: 45950 | D78: MJ62 JKN | E78: Smart | G78: Carwow | I78: 1600 | J78: 364.54 | K78: =SUM(I78:J78) -> 1964.54 | L78: 2650 | M78: =L78-SUM(I78:J78) -> 685.46 | N78: Sold
B79: 45931 | C79: 45950 | D79: YT63 ENJ | E79: Smart | I79: 1500 | K79: =SUM(I79:J79) -> 1500
B80: 45931 | C80: 45959 | D80: DP64CXV | E80: Fiat 500 | I80: 2000 | K80: =SUM(I80:J80) -> 2000
B81: 45931 | C81: 45960 | D81: WM63 XCE | E81: Fiat 500 | I81: 1400 | K81: =SUM(I81:J81) -> 1400
B82: 45931 | C82: 45961 | D82: ET15 BWO | E82: Audi A5 | I82: 4250 | K82: =SUM(I82:J82) -> 4250
B83: 45931
B84: 45962 | C84: 45807 | D84: WD63NXU | E84: Nissan Navara | F84: SA | G84: FB | I84: 2000 | J84: =SUM('Nissan Navara WD63 NXU'!B3:B80) -> 4737.99 | K84: =SUM(I84:J84) -> 6737.99 | N84: On Sale
B85: 45962 | C85: 45859 | D85: KE65XBC | E85: Seat Ibiza | F85: SA | G85: FB | I85: 1200 | J85: 2451.52 | K85: =SUM(I85:J85) -> 3651.52 | L85: 3550 | M85: =L85-SUM(I85:J85) -> -101.52 | N85: Sold
B86: 45962 | C86: 45860 | D86: BD66AOL | E86: Ford C-Max | F86: Leonardo | G86: Copart | I86: 4387.08 | J86: 1648.79 | K86: =SUM(I86:J86) -> 6035.87 | L86: 6300 | M86: =L86-SUM(I86:J86) -> 264.13 | N86: Sold
B87: 45962 | C87: 45873 | D87: EA65NDL | E87: Ford Fiesta | F87: James | G87: FB | I87: 2250 | J87: =350+400+180 -> 930 | K87: =SUM(I87:J87) -> 3180 | N87: Sold
B88: 45962 | C88: 45928 | D88: KU11 GRZ | E88: Skoda Fabia VRS | F88: SA | G88: Carwow | H88: Polo - HG57 MDE | I88: 2100 | J88: 1049.04 | K88: =SUM(I88:J88) -> 3149.04 | L88: 3795 | M88: =L88-SUM(I88:J88) -> 645.96 | N88: Sold
B89: 45962 | C89: 45929 | D89: MM17 XOZ | E89: Nissan Leaf | F89: Jeff | G89: Carwow | I89: 3400 | J89: 986.43 | K89: =SUM(I89:J89) -> 4386.43 | L89: 5394 | M89: =L89-SUM(I89:J89) -> 1007.57 | N89: Sold
B90: 45962 | C90: 45931 | D90: MK59 FUV | E90: Ford Fiesta | F90: Daniel | G90: Carwow | I90: 3100 | J90: =SUM('Ford Fiesta MK59 FUV'!B3:B15) -> 849.35 | K90: =SUM(I90:J90) -> 3949.35 | L90: 5795 | M90: =L90-SUM(I90:J90) -> 1845.65 | N90: Sold
B91: 45962 | C91: 45935 | D91: PK64 LRL | E91: Nissan Juke | F91: Daniel | G91: Facebook | I91: 1500 | J91: 2016.24 | K91: =SUM(I91:J91) -> 3516.24 | L91: 5591.61 | M91: =L91-SUM(I91:J91) -> 2075.37 | N91: Sold
B92: 45962 | C92: 45947 | D92: HY10 RRO | E92: Nissan Note | F92: SA | G92: Carwow | I92: 1400 | J92: =783.05+238.8 -> 1021.85 | K92: =SUM(I92:J92) -> 2421.85 | L92: 2989.66 | M92: =L92-SUM(I92:J92) -> 567.81 | N92: Sold
B93: 45962 | C93: 45948 | D93: DV62 OYH | E93: Volkswagen Polo | F93: James | G93: Carwow | I93: 3800 | J93: 742.54 | K93: =SUM(I93:J93) -> 4542.54 | L93: 5795 | M93: =L93-SUM(I93:J93) -> 1252.46 | N93: Sold
B94: 45962 | C94: 45950 | D94: MJ15 EFS | E94: Volkswagen Polo | F94: James | G94: Carwow | I94: 4400 | J94: =843.21+280 -> 1123.21 | K94: =SUM(I94:J94) -> 5523.21 | L94: 6795 | M94: =L94-SUM(I94:J94) -> 1271.79 | N94: Sold
B95: 45962 | C95: 45950 | D95: YT63 ENJ | E95: Smart | F95: James | G95: Carwow | I95: 1500 | J95: =SUM('Smart Fortwo YT63 ENJ (B)'!B3:B21) -> 1076 | K95: =SUM(I95:J95) -> 2576 | L95: 3900 | M95: =L95-SUM(I95:J95) -> 1324 | N95: Sold
B96: 45962 | C96: 45959 | D96: DP64 CXV | E96: Fiat 500 | F96: Jeff | G96: Motorway | I96: 2000 | J96: =SUM('Fiat 500 DP64CXV White'!B3:B19) -> 386.87 | K96: =SUM(I96:J96) -> 2386.87 | L96: 4695 | M96: =L96-SUM(I96:J96) -> 2308.13 | N96: Sold
B97: 45962 | C97: 45960 | D97: WM63 XCE | E97: Fiat 500 | F97: SA | G97: Carwow | I97: 1400 | J97: =SUM('Fiat 500 WM63 XCE Grey'!B3:B9) -> 1131.61
B98: 45962 | C98: 45961 | D98: ET15 BWO | E98: Audi A5 | F98: Joseph | G98: Carwow | I98: 4250 | J98: =SUM('Audi A5 ET65 BWO'!B3:B10) -> 1187.63 | K98: =SUM(I98:J98) -> 5437.63 | L98: 8602 | M98: =L98-SUM(I98:J98) -> 3164.37 | N98: Sold
B99: 45962 | C99: 45965 | D99: KM17 YTV | E99: Nissan Qashqai | F99: Henry | G99: Carwow | I99: =4250 -> 4250 | J99: =SUM('Nissan Qashqai KM17 YTV'!B3:B19) -> 4111.51 | K99: =SUM(I99:J99) -> 8361.51
B100: 45962 | C100: 45970 | D100: JFZ 1824 | E100: Volkswagen Polo | F100: James | G100: Carwow | I100: 4252.51 | J100: =SUM('Volkswagen Polo JFZ 1824'!B3:B26) -> 643.29 | K100: =SUM(I100:J100) -> 4895.8
B101: 45962 | C101: 45975 | D101: YB65 XPP | E101: Fiat 500 | F101: Jeff | G101: Carwow | I101: 3500 | J101: =SUM('Fiat 500 YB65 XPP'!B3:B26) -> 779.18 | K101: =SUM(I101:J101) -> 4279.18
...

Sheet Collection
A1: Source | B1: Date Won | C1: Plate Number | D1: Make & Model | E1: Location | F1: Post Code | G1: How Far? | H1: Collection Date | I1: Number | J1: Additional notes
A2: Motorway | B2: 46119 | C2: AF65LAA | D2: Mercedes CLA250 | E2: Iverness | F2: IV362PN | G2: 10 hours. 😐 | H2: TBC
A3: Motorway | B3: 46119 | C3: SA17 ZGJ | D3: Volkswagen Passat GTE | E3: Edinburgh | F3: EH91UQ | G3: Near GTI | H3: TBC
A4: Motorway | B4: 46119 | C4: MJ69 CGU | D4: Tesla Model 3 Standard Range | E4: Manchester | J4: Awaiting confirmation
A5: Motorway | B5: 46116 | C5: ST63YUG | D5: Volkswagen Golf GTI | E5: Edinburgh | F5: EH222EL | G5: Near GTE | H5: TBC
A6: Carwow | B6: 46119 | C6: LO65 TSU | D6: Mercedes-Benz C220d | E6: Enfield | F6: EN8 8NQ | H6: TBC
C7: RK13 DOR | D7: Audi TTS | E7: Telford Birmingham | F7: TF28RW | G7: Grab after Tesla Pickup
G8: ,

Sheet Investor Budget
A1: Investors | B1: Initial Balance | C1: Capital Returned | D1: Total Balance | E1: Purchased | F1: Total Profit (since Nov-25) | G1: Available
A2: James | B2: =24531.81+7000 -> 31531.81 | C2: 0 | D2: =(Table19[[#This Row],[Initial Balance]]+Table19[[#This Row],[Total Profit (since Nov-25)]])-Table19[[#This Row],[Capital Returned]] -> 42250.05 | E2: =SUM('Stock Data'!K262,'Stock Data'!K263,'Stock Data'!K270,'Stock Data'!K271,'Stock Data'!K286) -> 33393.275 | F2: =SUMIF(Table13[[#All],[MP/Investor Name]],'Sold Stock'!E49,Table13[[#All],[Investor Profit]]) -> 10718.24 | G2: =Table19[[#This Row],[Total Balance]]-Table19[[#This Row],[Purchased]] -> 8856.7746
A3: Daniel | B3: =18905.56+5000 -> 23905.56 | C3: 0 | D3: =(Table19[[#This Row],[Initial Balance]]+Table19[[#This Row],[Total Profit (since Nov-25)]])-Table19[[#This Row],[Capital Returned]] -> 30862.171 | E3: =SUM('Stock Data'!K215,'Stock Data'!K220,'Stock Data'!K245,'Stock Data'!K285) -> 26829.95 | F3: =SUMIF(Table13[[#All],[MP/Investor Name]],'Sold Stock'!E55,Table13[[#All],[Investor Profit]]) -> 6956.6106 | G3: =Table19[[#This Row],[Total Balance]]-Table19[[#This Row],[Purchased]] -> 4032.2206
A4: Joseph | B4: =18460.57+18000 -> 36460.57 | C4: 548.41 | D4: =(Table19[[#This Row],[Initial Balance]]+Table19[[#This Row],[Total Profit (since Nov-25)]])-Table19[[#This Row],[Capital Returned]] -> 47209.495 | E4: =SUM('Stock Data'!K268,'Stock Data'!K279,'Stock Data'!K288,'Stock Data'!K289) -> 32758.29 | F4: =SUMIF(Table13[[#All],[MP/Investor Name]],'Sold Stock'!E57,Table13[[#All],[Investor Profit]]) -> 11297.335 | G4: =Table19[[#This Row],[Total Balance]]-Table19[[#This Row],[Purchased]] -> 14451.205
A5: Leonardo | B5: 4346.8 | C5: 458.74 | D5: =(Table19[[#This Row],[Initial Balance]]+Table19[[#This Row],[Total Profit (since Nov-25)]])-Table19[[#This Row],[Capital Returned]] -> 5104.0897 | E5: ='Stock Data'!K234 -> 5558.93 | F5: =SUMIF(Table13[MP/Investor Name],'Sold Stock'!E47,Table13[Investor Profit]) -> 1216.0297 | G5: =Table19[[#This Row],[Total Balance]]-Table19[[#This Row],[Purchased]] -> -454.84033
A6: Jeff | B6: 20000 | C6: 1326.28 | D6: =(Table19[[#This Row],[Initial Balance]]+Table19[[#This Row],[Total Profit (since Nov-25)]])-Table19[[#This Row],[Capital Returned]] -> 25507.265 | E6: ='Stock Data'!K276 -> 6701.75 | F6: =SUMIF(Table13[MP/Investor Name],'Sold Stock'!E48,Table13[Investor Profit]) -> 6833.5447 | G6: =Table19[[#This Row],[Total Balance]]-Table19[[#This Row],[Purchased]] -> 18805.515
A7: Adam | B7: 15000 | C7: 623.23 | D7: =(Table19[[#This Row],[Initial Balance]]+Table19[[#This Row],[Total Profit (since Nov-25)]])-Table19[[#This Row],[Capital Returned]] -> 15000 | E7: ='Stock Data'!K244+'Stock Data'!K250 -> 12412.79 | F7: 623.23 | G7: =Table19[[#This Row],[Total Balance]]-Table19[[#This Row],[Purchased]] -> 2587.21
A8: Anthony | B8: 10000 | D8: =(Table19[[#This Row],[Initial Balance]]+Table19[[#This Row],[Total Profit (since Nov-25)]])-Table19[[#This Row],[Capital Returned]] -> 10000 | G8: =Table19[[#This Row],[Total Balance]]-Table19[[#This Row],[Purchased]] -> 10000
C10: Total Capital | D10: =SUM(D2:D8) -> 175933.07 | F10: Total Available | G10: =SUMIF(G2:G9, ">5000") -> 52113.494

Sheet SOR
A1: Month | B1: Date Aquired | C1: Number Plate reference | D1: Make & Model | E1: Seller Name | F1: Total Cost | G1: Sale Price | H1: Breakdown
A2: 45962 | C2: MJ62 JKN | D2: Smart Car | E2: Peggie | F2: =15+17.95+40+8+52.45 -> 133.4 | G2: 4000 | H2: 52.45 warranty, 40 MOT, 8 wash, 17.95 insurance, 15 carwash
A3: 45962 | C3: SW58FTK | D3: Golf | E3: HAVERN | F3: 143.72 | G3: 1900 | H3: 20 Wash, 92 Warranty, 31.72 v62
A4: 45992 | C4: SR68 UTW | D4: Golf-E | E4: Daniella | F4: =8.55+8+6.49+69.95+25+195 -> 312.99 | G4: 8190 | H4: 8.55 part, 8 wash, 6.49 Tow cover, warranty 69.95, v62 £25, £195 tax
F6: 40 | H6: FX63VBV Golf
F7: 100 | H7: MS66 SUL

Sheet Investor Car Expense
A1: Month | B1: Date | C1: Reason | D1: Amount | E1: Reg
A2: 46023 | B2: 46037 | C2: Jatin Driver | D2: 80 | E2: Smart Premuim SR16 HKT
A3: 46023 | B3: 46040 | C3: Detailer | D3: 100 | E3: Detailer Fiat LK15, Quashkai, Octovia, Smart
A4: 46023 | B4: 46050 | C4: Detailer | D4: 100 | E4: BMW 518d, Polo MF14, BMW 120d, Peugeot 2008
A5: 46023 | B5: 46051 | C5: Adam Driver | D5: 90 | E5: Peugeot 2008, Audi A1 Drop off, BMW 328i
A6: 46023
A7: 46023
A8: 46023 | C8: Expense Incurred | D8: =SUM(D2:D6) -> 370
A9: 46023
A10: 46054 | C10: Kassim | D10: 80 | E10: EN63 TKA
A11: 46054 | C11: Train | D11: 56.48 | E11: EN63 TKA
A12: 46054 | C12: Uber | D12: 28.93 | E12: EN63 TKA
A13: 46054 | C13: Uber | D13: 5.93 | E13: MF15 OPJ
A14: 46054 | C14: TFL | D14: =3.8+12.5 -> 16.3 | E14: MF15 OPJ + EJ14 PTX
A15: 46054 | C15: Train | D15: 113.27 | E15: MF15 OPJ + EJ14 PTX
A16: 46054 | C16: Uber | D16: 48.95 | E16: YY65 CAU, S88 RDF, LS66 SVA
A17: 46054 | C17: Kassim | D17: 120 | E17: YY65 CAU, S88 RDF, LS66 SVA
A18: 46054 | B18: 46062 | C18: Detailer | D18: 75 | E18: Mocha, S88 RDF, PE65 LXZ
A19: 46054 | C19: Kassim | D19: 90 | E19: WA13XCV
A20: 46054 | C20: Kassim | D20: 90 | E20: BJ64 OSE, A6
A21: 46054 | C21: Kassim | D21: 45 | E21: VX16 XJU, LJ13 UAC
A22: 46054 | C22: Flight | D22: 67.99 | E22: KM62 XFN
A23: 46054
A24: 46054
A25: 46054 | C25: Expense Incurred | D25: =SUM(D10:D24) -> 837.85
A26: 46054
A27: 46082 | C27: Pick-Up | D27: =54.95+18.5 -> 73.45 | E27: KM62 XFN
A28: 46082 | C28: Detailer | D28: 35 | E28: WA13 XCV
A29: 46082 | C29: Kasim | D29: 90 | E29: BG63 VYM
A30: 46082 | C30: Flight | D30: 117.98 | E30: KU67 PWY & FY67 WDE
A31: 46082 | C31: Bus | D31: 22.5 | E31: KU67 PWY & FY67 WDE
A32: 46082 | C32: Uber | D32: 38.93 | E32: KU67 PWY & FY67 WDE
A33: 46082 | C33: Insurance | D33: 15.37 | E33: KU67 PWY & FY67 WDE
A34: 46082 | C34: Kasim | D34: 120 | E34: KU67 PWY & FY67 WDE
A35: 46082 | C35: Adam | D35: 80 | E35: AY17 YWX
A36: 46082 | C36: Adam | D36: 80 | E36: WU66 MJX
A37: 46082
A38: 46082 | C38: Expense Incurred | D38: =SUM(D27:D37) -> 673.23
A39: 46082
A40: 46113 | D40: 20 | E40: FY67 WDE
A41: 46082 | D41: 38.6 | E41: Driver
A42: 46113
A43: 46113
A44: 46113
A45: 46113
A46: 46113
A47: 46113
A48: 46113
A49: 46113
A50: 46113
A51: 46113
A52: 46113
A53: 46113
... A55: 46113
A56: 46113 | C56: Expense Incurred | D56: =SUM(D40:D55) -> 58.6
A57: 46113

Sheet Expense
A1: Month | B1: Date | C1: Category | D1: From | E1: Amount | F1: Payment Method | G1: Paid By | H1: Notes
A2: 45809 | B2: 45822 | C2: Variable Cost | D2: Autotrader hpi | E2: 4.95 | F2: Debit Card | G2: Business | H2: RE62VVC
A3: 45809 | C3: Fixed Overhead | E3: 49.99 | F3: Debit Card | G3: Mussey | H3: Car Huntr
A4: 45809 | C4: Variable Cost | D4: COS | E4: 19.99 | F4: Debit Card | G4: Business | H4: HPI Checks
A5: 45809 | B5: 45819 | C5: Variable Cost | D5: Parts | E5: 12.78 | F5: Debit Card | G5: Business | H5: Polish liquid
A6: 45809 | B6: 45822 | C6: Fixed Overhead | E6: 32.4 | F6: Debit Card | G6: Business | H6: Partslink
A7: 45809 | B7: 45825 | C7: Variable Cost | D7: Autotrader hpi | E7: 4.95 | F7: Debit Card | G7: Business | H7: FL11LXD
A8: 45809 | B8: 45834 | C8: Variable Cost | D8: Autotrader hpi | E8: 4.95 | F8: Debit Card | G8: Business | H8: SO13EXH
A9: 45809 | B9: 45835 | C9: Variable Cost | D9: Autotrader hpi | E9: 4.95 | F9: Debit Card | G9: Business | H9: BK10JXB
A10: 45809 | B10: 45835 | C10: Variable Cost | D10: Autotrader hpi | E10: 4.95 | F10: Debit Card | G10: Business | H10: AV57MFN
A11: 45809
A12: 45809 | D12: Total Expense | E12: =SUM(E2:E10) -> 139.91
A14: 45839 | B14: 45856 | D14: Nasir | E14: 130 | F14: Bank Transfer | G14: Poppy | H14: Not paid back - Funpack Recovery
A15: 45839 | B15: 45859 | C15: Variable Cost | D15: AutoTrader HPI | E15: 4.95 | F15: Debit Card | G15: Poppy | H15: Not paid back - Not purchased
A16: 45839 | B16: 45861 | C16: Variable Cost | D16: Autotrader hpi | E16: 4.95 | F16: Debit Card | G16: Business | H16: LN06ZWP
A17: 45839 | D17: Nasir | F17: Debit Card | G17: Business | H17: Not paid back - Insurance
A18: 45839 | B18: 45865 | D18: Fine | E18: 160 | F18: Debit Card | G18: Business | H18: BMW
A19: 45839 | B19: 45865 | D19: Amazon | E19: 18.8 | F19: Debit Card | G19: Business | H19: Hoover Payment
A20: 45839 | C20: Variable Cost | D20: Transport | E20: 1.75 | F20: Debit Card | G20: Business | H20: TFL
A21: 45839 | B21: 45868 | D21: Petrol Station | E21: 1.49 | F21: Debit Card | G21: Business | H21: Tape Audi Bumper
A22: 45839 | B22: 45868 | D22: Petrol Station | E22: 3.98 | F22: Debit Card | G22: Business | H22: 4L Water Audi Coolant
A23: 45839 | B23: 45868 | C23: Variable Cost | D23: Transport | E23: 25.99 | F23: Debit Card | G23: Business | H23: Uber
A24: 45839 | B24: 45868 | D24: Food/Drink | E24: 1.65 | F24: Debit Card | G24: Business | H24: Londis - Mo Monster
A25: 45839 | B25: 45868 | C25: Variable Cost | D25: Transport | E25: 3.1 | F25: Debit Card | G25: Business | H25: TFL
A26: 45839 | B26: 45869 | C26: Variable Cost | D26: Transport | E26: 24.6 | F26: Debit Card | G26: Business | H26: TFL
A27: 45839 | B27: 45869 | C27: Variable Cost | D27: Autotrader hpi | E27: 4.95 | F27: Debit Card | G27: Business | H27: BK12LTU
A28: 45839
A29: 45839 | D29: Total Expense | E29: =SUM(E14:E27) -> 386.21
E30: #
A31: 45870 | B31: 45870 | D31: Transport | E31: 1.75 | F31: Debit Card | G31: Business | H31: TFL
A32: 45870 | B32: 45871 | D32: Halfords | E32: 27.99 | F32: Debit Card | G32: Business | H32: Car Cover
A33: 45870 | B33: 45872 | C33: Fixed Overhead | D33: COS | E33: 128.5 | F33: Debit Card | G33: Business | H33: Virtual Office + Mail
A34: 45870 | B34: 45873 | C34: Fixed Overhead | D34: COS | E34: 8.5 | F34: Debit Card | G34: Business | H34: Barclays Business Account
A35: 45870 | B35: 45874 | C35: Fixed Overhead | D35: COS | E35: 70.8 | F35: Debit Card | G35: Business | H35: Spidersnet Website
A36: 45870 | B36: 45875 | E36: 80.92 | F36: Debit Card | G36: Business | H36: Van Hire Fuel
A37: 45870 | B37: 45875 | D37: Post Office | E37: 2.8 | F37: Debit Card | G37: Business | H37: Barclays Letter
A38: 45870 | B38: 45878 | D38: Parts | E38: 44.18 | F38: Debit Card | G38: Business | H38: Euro Car Parts Coolant A5
A39: 45870 | B39: 45878 | D39: Parts | E39: 40 | F39: Debit Card | G39: Business | H39: Transmission Oil A5
A40: 45870 | B40: 45879 | D40: Parts | E40: 39.95 | F40: Debit Card | G40: Business | H40: Headlight Bracket A5
A41: 45870 | B41: 45884 | D41: Tiktok | E41: 9.33 | F41: Debit Card | G41: Business | H41: Polarised Filter
A42: 45870 | B42: 45886 | D42: AutoTrader HPI | E42: 4.95 | F42: Debit Card | G42: Business | H42: Not purchased
A43: 45870 | B43: 45889 | D43: Parking Permit | E43: 10 | F43: Debit Card | G43: Business | H43: A5 Permit Transfer
A44: 45870 | B44: 45891 | D44: AutoTrader HPI | E44: 4.95 | F44: Debit Card | G44: Business | H44: Not purchased
A45: 45870 | B45: 45891 | C45: Variable Cost | D45: AutoTrader HPI | E45: 4.95 | F45: Debit Card | G45: Business | H45: Not purchased
A46: 45870 | B46: 45894 | C46: Fixed Overhead | D46: BCA | E46: 118.8 | F46: Debit Card | G46: Business | H46: Account Signup
A47: 45870 | C47: Fixed Overhead | E47: 39.99 | H47: Car hunter
A48: 45870 | C48: Variable Cost | D48: AutoTrader HPI | E48: 4.95
A49: 45870
A50: 45870 | D50: Total Expense | E50: =SUM(E31:E48) -> 643.31
A52: 45901 | B52: 45901 | C52: Operating Cost | D52: Shell | E52: 1.75 | F52: Debit Card | G52: Business | H52: Water
A53: 45901 | B53: 45901 | C53: Operating Cost | D53: Shell | E53: 7.95 | F53: Debit Card | G53: Business | H53: Charger
A54: 45901 | B54: 45916 | C54: Operating Cost | D54: Petrol Station | E54: 3.05 | F54: Debit Card | G54: Business | H54: Coffee
A55: 45901 | B55: 1st | D55: Asda | E55: 6.85 | F55: Debit Card | G55: Business | H55: Towels + Cookies
A56: 45901 | B56: 1st | D56: DVLA | E56: 23.18 | F56: Debit Card | G56: Business | H56: Tax FL11LXD
A57: 45901 | B57: 2nd | D57: Chat GPT | E57: 19.99 | F57: Debit Card | G57: Business | H57: 1 Month Subscription
A58: 45901 | B58: 3rd | D58: eBay | E58: 19.42 | F58: Debit Card | G58: Business | H58: Paper Floormats
A59: 45901 | B59: 3rd | D59: DVLA | E59: 34.15 | F59: Debit Card | G59: Business | H59: TAX LS15HLO
A60: 45901 | B60: 3rd | D60: SpydersNet | E60: 70.8 | F60: Debit Card | G60: Business | H60: Website
A61: 45901 | B61: 4th | D61: Auto Trader | E61: 4.95 | F61: Debit Card | G61: Business | H61: Ibiza
A62: 45901 | B62: 4th | D62: HPI Check | E62: 4.95 | F62: Debit Card | G62: Business | H62: Fiat 500 Abdullah
A63: 45901 | B63: 5th | D63: Barclays | E63: 46.87 | F63: Debit Card | G63: Business | H63: Nasir Deposit + Monthly Charge
A64: 45901 | B64: 13th | D64: eBay | E64: 8.99 | F64: Debit Card | G64: Business | H64: VW Centre Wheel cap polo
A65: 45901 | B65: 15th | D65: Admiral | E65: 214.67 | F65: Debit Card | G65: Business | H65: Insurance A5
A66: 45901 | B66: 16th | D66: Petrol Station | E66: 3.05 | F66: Debit Card | G66: Business | H66: Coffee
... A73: 45901 | B73: 29th | D73: Amazon | E73: 52.99 | F73: Debit Card | G73: Business | H73: storage box
A74: 45901 | D74: Barclays | E74: 9.7 | F74: Debit Card | G74: Business | H74: Account Fee
A75: 45901
A76: 45901 | D76: Total Expense | E76: =SUM(E52:E74) -> 854.31
A77: 45901
A78: 45931 | B78: 45933 | C78: Fixed Overhead | D78: Admin | E78: 20 | F78: Debit Card | G78: Business | H78: ChatGPT
A79: 45931 | B79: 45933 | D79: eBay | E79: 8.64 | F79: Debit Card | G79: Business | H79: Review Cards
A80: 45931 | B80: 45933 | C80: Fixed Overhead | D80: Spidersnet | E80: 70.8 | F80: Debit Card | G80: Business | H80: Website
A81: 45931 | B81: 45934 | C81: Operating Cost | D81: Wickes | E81: 30.33 | F81: Debit Card | G81: Business | H81: Cement
A82: 45931 | B82: 45934 | C82: Operating Cost | D82: B&Q | E82: 26.1 | F82: Debit Card | G82: Business | H82: Cement
A83: 45931 | B83: 45935 | C83: Operating Cost | D83: Selco Builders | E83: 13.8 | F83: Debit Card | G83: Business | H83: Plaster Board
A84: 45931 | B84: 45935 | C84: Operating Cost | D84: Wickes | E84: 6.66 | F84: Debit Card | G84: Business | H84: Cement
A85: 45931 | B85: 45936 | C85: Fixed Overhead | D85: eBay | E85: 16.99 | F85: Debit Card | G85: Business | H85: SA Merch
A86: 45931 | B86: 45936 | D86: Barclays | E86: 9.7 | F86: Debit Card | G86: Business | H86: Charges
A87: 45931 | B87: 45940 | D87: Cargurus | E87: 260 | F87: Debit Card | G87: Business | H87: Ads Package
A88: 45931 | B88: 45938 | C88: Fixed Overhead | D88: Rent | E88: 1950 | F88: Debit Card | G88: Business | H88: Unit
A89: 45931 | B89: 45941 | D89: Business Car | E89: 55 | F89: Cash | G89: Business | H89: Audi Tyre
A90: 45931 | B90: 45942 | D90: Wickes | E90: 7.99 | F90: Debit Card | G90: Business | H90: Office
A91: 45931 | B91: 45942 | D91: Toolstation | E91: 2 | F91: Debit Card | G91: Business | H91: Blu Tack
A92: 45931 | B92: 45942 | D92: Ziba Caffe | E92: 10 | F92: Cash | G92: Business | H92: Business Planning
A93: 45931 | B93: 45942 | D93: Wickes | E93: 40 | F93: Cash | G93: Business | H93: Wall Paper
A94: 45931 | B94: 45942 | D94: Insurance | E94: 214.67 | F94: Debit Card | G94: Business | H94: Audi
A95: 45931 | B95: 45943 | D95: Office | E95: 19.99 | F95: Debit Card | G95: Business | H95: Key Box
A96: 45931 | B96: 45943 | D96: TikTok Shop | E96: 7.99 | F96: Debit Card | G96: Business | H96: Car Phone Charger
A97: 45931 | B97: 45947 | D97: Admin | E97: 8.99 | F97: Debit Card | G97: Business | H97: Business Cards
A98: 45931 | B98: 45949 | D98: Wickes | E98: 10.5 | F98: Debit Card | G98: Business | H98: Adhesive Spray
A99: 45931 | B99: 45949 | D99: Office | E99: 5.94 | F99: Debit Card | G99: Business | H99: Floor Matt
A100: 45931 | B100: 45956 | D100: Office | E100: 23.01 | F100: Debit Card | G100: Business | H100: Heater
... A105: 45931 | B105: 45959 | D105: Office | E105: 20 | F105: Debit Card | G105: Business | H105: Chairs
A106: 45931
A107: 45931 | D107: Total Expense | E107: =SUM(E78:E105) -> 3132.29
A109: 45962 | D109: Food | E109: 40 | F109: Cash | G109: Business | H109: d's kitchen
A110: 45962 | D110: Food | E110: 15 | F110: Cash | G110: Business | H110: Chicken Shop
A111: 45962 | D111: Food | E111: 100 | F111: Bank Transfer | G111: Business | H111: Recovery for Corsa - Vehicle Sale Cancelled MF61 ECN Engine issues
A112: 45962 | D112: Food | E112: 35 | F112: Cash | G112: Business | H112: Pizza
A113: 45962 | C113: Fixed Overhead | D113: Audi | E113: 17.06 | F113: Direct Debit | G113: Business | H113: Audi Road Tax
...

Sheet Fuel Expense
A1: Month | B1: Date | C1: Car | D1: Amount | E1: Column1
A2: 45839 | B2: 45858 | C2: Fiesta | D2: 56.41
A3: 45839 | B3: 45861 | C3: Fiesta | D3: 35.19
A4: 45839 | B4: 45863 | C4: Fiesta | D4: 22.13
A5: 45839 | C5: Fiesta | D5: 30.02
A6: 45839 | B6: 45868 | C6: Audi | D6: 60
A7: 45839 | B7: 45857 | C7: Volvo | D7: 43.28
A8: 45839
A9: 45839 | C9: Total Fuel | D9: =SUM(D2:D7) -> 247.03
A11: 45870 | B11: 45870 | C11: Volvo | D11: 30.02
A12: 45870 | B12: 45874 | C12: Volvo | D12: 68.92
A13: 45870 | B13: 45875 | C13: Van Hire | D13: 80.92
A14: 45870 | B14: 45877 | C14: Fiesta | D14: 20.02
A15: 45870 | B15: 45883 | C15: Fiesta | D15: 10.74
A16: 45870 | B16: 45890 | C16: Audi A5 | D16: 51.27
A17: 45870 | B17: 45894 | C17: Audi A5 | D17: 77.45
A18: 45870 | B18: 45899 | C18: Audi A5 | D18: 70.4
A19: 45870
A20: 45870 | C20: Total Fuel | D20: =SUM(D11:D18) -> 409.74
A22: 45901 | B22: 45904 | C22: Audi A5 | D22: 71.44
A23: 45901 | B23: 45908 | C23: Audi A5 | D23: 71.9
A24: 45901 | B24: 45912 | C24: Audi A5 | D24: 40.07
A25: 45901 | B25: 45913 | C25: Audi A5 | D25: 20.01
A26: 45901 | B26: 45914 | C26: Audi A5 | D26: 75.12
A27: 45901 | B27: 45919 | C27: Audi A5 | D27: 73.28
A28: 45901 | B28: 45926 | C28: Audi A5 | D28: 10
A29: 45901 | B29: 45926 | C29: Audi A5 | D29: 73.19
A30: 45901
A31: 45901 | C31: Total Fuel | D31: =SUM(D22:D29) -> 435.01
A33: 45931 | B33: 45932 | C33: Audi | D33: 67.79
A34: 45931 | B34: 45938 | C34: Audi | D34: 75.67
A35: 45931 | B35: 45942 | C35: Audi | D35: 74.67
A36: 45931 | B36: 45948 | C36: Audi | D36: 79.41
A37: 45931 | B37: 45953 | C37: Audi | D37: 72.96
A38: 45931
A39: 45931 | C39: Total Fuel | D39: =SUM(D33:D37) -> 370.5
A41: 45962 | B41: 45977 | C41: Golf | D41: 45
A42: 45962 | B42: 45975 | C42: Audi | D42: 74.01
A43: 45962 | C43: Volvo | D43: 49.89
A44: 45962 | B44: 45980 | C44: Audi | D44: 78.3
A45: 45962 | B45: 45986 | C45: Audi | D45: 70.19
A46: 45962 | B46: 45988 | C46: Audi | D46: =20.14+5.2 -> 25.34
A47: 45962 | B47: 45991 | C47: Audi | D47: 80.04
A48: 45962
A49: 45962 | C49: Total Fuel | D49: =SUM(D41:D47) -> 422.77
A50: 45962
A51: 45992 | B51: 45995 | C51: Audi | D51: 79.95
A52: 45992 | B52: 45996 | C52: Audi | D52: 10.82
A53: 45992 | B53: 46000 | C53: Audi | D53: 78.71
A54: 45992 | B54: 46006 | C54: Audi | D54: 80.13
A55: 45992 | C55: Audi | D55: 81.63
A56: 45992
A57: 45992 | C57: Total Fuel | D57: =SUM(D51:D55) -> 331.24
A58: 45992
A59: 46023 | B59: 46023 | C59: Audi | D59: 76.26
A60: 46023 | B60: 46026 | D60: 18
A61: 46023 | B61: 46029 | C61: Golf | D61: 35.35
A62: 46023 | B62: 46028 | D62: 19.6
A63: 46023 | B63: 46029 | C63: Audi | D63: 75.8
A64: 46023 | B64: 46029 | D64: 3.23
A65: 46023 | B65: 46033 | C65: Golf | D65: 24.5
A66: 46023 | B66: 46033 | C66: Audi | D66: 69.28
A67: 46023 | B67: 46039 | C67: Audi | D67: 75.92
A68: 46023 | C68: Audi | D68: 75.92
A69: 46023 | B69: 46047 | C69: Audi | D69: 75.2
A70: 46023 | D70: 6.26
A71: 46023
A72: 46023 | C72: Total Fuel | D72: =SUM(D59:D68) -> 473.86
A73: 46023
A74: 46054 | B74: 46055 | C74: Audi | D74: 74.67
A75: 46054 | B75: 46057 | D75: 12.51
A76: 46054 | B76: 46057 | C76: Audi | D76: 75.97
A77: 46054 | B77: 46061 | D77: 10.33
A78: 46054 | B78: 46063 | C78: Audi | D78: 79.11
A79: 46054 | B79: 46063 | D79: 9.93
A80: 46054 | B80: 46065 | C80: Audi | D80: 81.31
A81: 46054 | B81: 46067 | C81: Audi | D81: 77.37
A82: 46054 | B82: 46073 | C82: Audi | D82: 63.58
A83: 46054 | B83: 46077 | C83: Audi | D83: 70
A84: 46054 | D84: 10.16
A85: 46054
A86: 46054 | C86: Total Fuel | D86: =SUM(D74:D84) -> 564.94
A87: 46054
A88: 46082 | C88: Audi | D88: 9.54
A89: 46082 | D89: 20.28 | E89: To be returned
A90: 46082 | D90: 60.54 | E90: To be returned
A91: 46082 | C91: Audi | D91: 17.91
A92: 46082 | C92: Audi | D92: 8.06
A93: 46082 | C93: Audi | D93: 87.89
A94: 46082 | C94: Audi | D94: 90.02
A95: 46082 | C95: Audi | D95: 77.64
A96: 46082 | D96: 78.97
A97: 46082 | D97: 95.56
A98: 46082
A99: 46082 | C99: Total Fuel | D99: =SUM(D88:D97) -> 546.41
A101: 46113 | D101: 97.79
A102: 46113
A103: 46113
A104: 46113
A105: 46113
...

Sheet Money in
A1: Month | B1: Date | C1: Category | D1: Amount | E1: Reg | F1: Notes
A2: 45962 | B2: 45975 | C2: Deposit | D2: 200 | E2: Card | F2: Depo not refunded
A3: 45962 | B3: 45988 | C3: Delivery Fee | D3: 164.32 | E3: ET15 BWO | F3: Delivery Fee Audi A5, ET15 BWO
A4: 45962
A5: 45962 | C5: Total Money In | D5: =SUM(D2:D3) -> 364.32
A6: 45962
A7: 45992 | C7: Transfer | D7: 395 | F7: Impound Fee
A8: 46011 | B8: 46011 | C8: SOR Sale | D8: =300-31.72 -> 268.28
A9: 46011
A10: 46011 | C10: Total Money In | D10: =SUM(D7:D9) -> 663.28
A11: 46011
A12: 46023 | D12: 250 | F12: Depo not refunded for Audi A1
A13: 46023
A14: 46023
A15: 46023 | C15: Total Money In | D15: =SUM(D12:D14) -> 250
A16: 46023
A17: 46054 | C17: SOR Sale | D17: 357.01 | F17: E-Golf sale
A18: 46054 | D18: 99 | E18: EN63 TKA | F18: Admin Fee
A19: 46054 | D19: =151+99 -> 250 | E19: YY65 CAU | F19: Admin Fee+Delivery £151
A20: 46054 | D20: 99 | E20: FV14 MYL | F20: Admin Fee
A21: 46054 | D21: 75.94 | F21: EBAY Return
A22: 46054 | D22: 700 | E22: OV61WKH | F22: Car return
A23: 46054
A24: 46054 | C24: Total Money In | D24: =SUM(D17:D23) -> 1580.95
A25: 46054
A26: 46082 | D26: 99 | E26: FV14 MYL | F26: Admin Fee
A27: 46082 | D27: 99 | E27: DP14 WEP | F27: Admin Fee
A28: 46082 | D28: 99 | E28: VK62 THV | F28: Admin Fee
A29: 46082
A30: 46082 | C30: Total Money In | D30: =SUM(D26:D29) -> 297
A31: 46082
A32: 46113 | D32: =99+80 -> 179 | E32: FN62 HKO | F32: Admin Fee & Delivery
A33: 46113
A34: 46113
A35: 46113
A36: 46113 | C36: Total Money In | D36: =SUBTOTAL(109,D32:D35) -> 179

Sheet Cash Spending
A1: Month | B1: Amount | C1: Cost Incurred on | D1: Reason
A2: 45962 | B2: 2600 | C2: Office | D2: Container
A3: 45962 | B3: 20 | C3: MM17 XOZ | D3: Nissan Leaf Car Wash
A4: 45962 | B4: 45 | D4: Fuel
A5: 45962
A6: 45962 | C6: Cash
A7: 45992 | B7: 600 | C7: Office | D7: Lights
A8: 45992 | B8: 220 | C8: BMW | D8: Alloys
A9: 45992 | B9: 3600 | C9: Office | D9: Rent + Deposit
A10: 45992 | B10: 40 | C10: Fiat 500, LM64 | D10: MOT
A11: 45992 | B11: 60 | C11: Office | D11: Printer
A12: 45992 | B12: 40 | C12: Office | D12: Drawers
A13: 45992 | B13: 270 | C13: HG57 | D13: bODYWORK + Spark Plugs
A14: 45992
A15: 45992
A16: 46023 | B16: 280 | C16: Polo MJ15 | D16: Mechanic Polo
A17: 46023 | B17: 140 | C17: PE65 LXZ | D17: BMW 120D Tyre
A18: 46023 | B18: 40 | C18: PE65 LXZ | D18: MOT BMW 120D
A19: 46023 | B19: 320 | C19: MF15 FUH | D19: Electrician
A20: 46023 | B20: 150 | C20: DN16 YXF | D20: Bodywork Outlander
A21: 46023 | B21: 15 | C21: CE65 MJJ | D21: Polo GT
A22: 46023 | B22: 15 | C22: EJ14 | D22: BMW Car wash
A23: 46023 | B23: 260 | C23: EJ14 | D23: Bodywork BMW
A24: 46023 | B24: 300 | C24: YB68 XYT | D24: Bodywork Skodia VRS
A25: 46023 | B25: 310 | C25: EJ14 | D25: JR Alloys BMW
A26: 46023
A27: 46054 | B27: 150 | C27: MF14 TUH | D27: Bodywork
A28: 46054 | B28: 100 | C28: PE65 LXZ | D28: Bodywork
A29: 46054 | B29: 250 | C29: WJ62 UVS | D29: Bodywork
A30: 46054 | B30: 250 | C30: YB61 MHX | D30: Bodywork
A31: 46054 | B31: 30 | D31: Steering wheel - Mocha
A32: 46054 | B32: 2500 | D32: Rent
A33: 46054 | B33: 40 | D33: James Gatwick - Scotland
A34: 46054 | B34: 240 | C34: YB61 MHX | D34: Alloys
A35: 46054 | B35: 160 | C35: FV14 MYL | D35: Alloys
A36: 46054 | B36: 10 | C36: PE65 LXZ | D36: JR Alloys BMW
A37: 46054 | B37: 250 | C37: EJ14 PTX | D37: Bodywork
A38: 46054 | B38: 50 | C38: VK62 THV | D38: Bodywork
A39: 46054 | B39: 200 | C39: LS13 UKA | D39: Bodywork
A40: 46054
A41: 46113 | B41: 2500 | D41: Rent
A42: 46113 | B42: 540 | C42: MS66UL, MK14 XVX, BG63VYM | D42: Alloy refurb
A43: 46113
A44: 46113
A45: 46113
A46: 46113
A47: 46113
A48: 46113
A49: 46113
A50: 46113
A51: 46113
A52: 46113

Sheet Money Out
A1: Month | B1: Date | C1: Category | D1: Amount | E1: Notes
A2: 45962 | B2: 45991 | C2: Money taken out by SA CASH | D2: 500 | E2: £250 Poppy, £250 Mussey from Nissan Mirca
A3: 45962
A4: 45962 | C4: Total Money Out | D4: =SUM(D2:D2) -> 500
A6: 46023 | B6: 46027 | C6: Mussey | D6: 1700 | E6: Director Loan Repayment
A7: 46023 | B7: 46027 | C7: Poppy | D7: 514.74 | E7: Director Loan Repayment
A8: 46023
A9: 46023 | C9: Total Money Out | D9: =SUM(D6:D7) -> 2214.74
A10: 46023
A11: 46107 | B11: 46107 | C11: Mussey | D11: 1000 | E11: Cash
A12: 46107 | B12: 46107 | C12: Poppy | D12: 1000 | E12: Cash
C14: Total Money Out | D14: =SUM(D11:D12) -> 2000

Sheet Kia Sportage ML20 YZW
A1: Item | B1: Amount | D1: Total Cost | E1: =SUM(B$2:B$1048576) -> 6530.8
A2: Price | B2: 6100 | D2: Sold For
A3: Fees | B3: 430.8 | D3: Profit / Loss | E3: =E2-E1 -> -6530.8

Sheet 520D M Sport RJ65 VVN
A1: Item | B1: Amount | D1: Total Cost | E1: =SUM(B$2:B$1048576) -> 7406.8
A2: Price | B2: 7000 | D2: Sold For
A3: Fees | B3: 406.8 | D3: Profit / Loss | E3: =E2-E1 -> -7406.8

Sheet 520D Lux NG64 EOH
A1: Item | B1: Amount | D1: Total Cost | E1: =SUM(B$2:B$1048576) -> 7648.77
A2: Price | B2: 6900 | D2: Sold For
A3: Fees | B3: 382.8 | D3: Profit / Loss | E3: =E2-E1 -> -7648.77
A4: Alloys | B4: 365.97

Sheet A6 YY62 XJW
A1: Item | B1: Amount | D1: Total Cost | E1: =SUM(B$2:B$1048576) -> 5332.8
A2: Price | B2: 4900 | D2: Sold For
A3: Fees | B3: 382.8 | D3: Profit / Loss | E3: =E2-E1 -> -5332.8
A4: Wash | B4: 10
A5: Kasim | B5: 40

Sheet A6 Allroad DL15 WDA 
A1: Item | B1: Amount | D1: Total Cost | E1: =SUM(B$2:B$1048576) -> 7632.6
A2: Price | B2: 7000 | D2: Sold For
A3: Fees | B3: 406.8 | D3: Profit / Loss | E3: =E2-E1 -> -7632.6
A4: fuel | B4: =54.67+9.42 -> 64.09
A5: Toll | B5: 11.6
A6: fuel | B6: 10.11
A7: TINTS | B7: 140

Sheet A3 E-Tron KM64 XCX
A1: Item | B1: Amount | D1: Total Cost | E1: =SUM(B$2:B$1048576) -> 6861.48
A2: Price | B2: 6000 | D2: Sold For | E2: 10596
A3: Fees | B3: 406.8 | D3: Profit / Loss | E3: =E2-E1 -> 3734.52
A4: Fuel | B4: =32.41+5.44+18.08 -> 55.93
A5: Toll | B5: 11.6
A6: fuel | B6: 7.15
A7: Alloy refurb | B7: 380

Sheet Audi A6 VE16 TNO
A1: Item | B1: Amount | D1: Total Cost | E1: =SUM(B$2:B$1048576) -> 6720.095
A2: Price | B2: 5950 | D2: Sold For
A3: Fees | B3: 406.8 | D3: Profit / Loss | E3: =E2-E1 -> -6720.095
A4: Flight | B4: =121.98/2 -> 60.99
A5: Ferry | B5: 178.07
A6: toll | B6: =2.06+3.12 -> 5.18
A7: UBER | B7: =45.95/2 -> 22.975
A8: FUEL | B8: =(40+20+50+30.28)/2 -> 70.14
A9: FUEL | B9: 15.66
A10: FUEL | B10: 10.28

Sheet CLA Estate YR16 XCB
A1: Item | B1: Amount | D1: Total Cost | E1: =SUM(B$2:B$1048576) -> 7481.425
A2: Price | B2: 6500 | D2: Sold For
A3: Fees | B3: 406.8 | D3: Profit / Loss | E3: =E2-E1 -> -7481.425
A4: Flight | B4: =121.98/2 -> 60.99
A5: Ferry | B5: 178.07
A6: Fuel | B6: 50.01
A7: Air | B7: 1.5
A8: wash | B8: 16
A9: fuel | B9: 9.76
A10: toll | B10: =2.06+3.12 -> 5.18
A11: UBER | B11: =45.95/2 -> 22.975
A12: FUEL | B12: =(40+20+50+30.28)/2 -> 70.14
A13: Bodywork | B13: 150
A14: fuel | B14: 10

Sheet Smart X65 YJL
A1: Item | B1: Amount | D1: Total Cost | E1: =SUM(B$2:B$1048576) -> 6194.8
A2: Price | B2: 5700 | D2: Sold For
A3: Fees | B3: 406.8 | D3: Profit / Loss | E3: =E2-E1 -> -6194.8
A4: Wash | B4: 8
A5: Driver | B5: 80

Sheet Kuga EJ68 WVM
A1: Item | B1: Amount | D1: Total Cost | E1: =SUM(B$2:B$1048576) -> 6454.8
A2: Price | B2: 5400 | D2: Sold For
A3: Fees | B3: 406.8 | D3: Profit / Loss | E3: =E2-E1 -> -6454.8
A4: Coolant leak | B4: 60
A5: Wash | B5: 80
A6: Bodywork | B6: 500
A7: wash | B7: 8

Sheet LY18 ZDV A200D
A1: Item | B1: Amount | D1: Total Cost | E1: =SUM(B$2:B$1048576) -> 8347.32
A2: Price | B2: ='Sold Stock'!F116 -> 8246.7 | D2: Sold For
A3: Fuel | B3: 7.03 | D3: Profit / Loss | E3: =E2-E1 -> -8347.32
A4: Alloy | B4: 80
A5: Badge | B5: 13.59

Sheet Merc C220D SE66 OFZ
A1: Item | B1: Amount | D1: Total Cost | E1: =SUM(B$2:B$1048576) -> 9186.03
A2: Price | B2: 7964 | D2: Sold For
A3: Fees | B3: 442.8 | D3: Profit / Loss | E3: =E2-E1 -> -9186.03
A4: Train | B4: 24.95
A5: Uber | B5: 7.95
A6: Fuel | B6: 32.33
A7: Toll | B7: 11.4
A8: TFL | B8: 3.3
A9: Bodywork | B9: 400
A10: Fuel | B10: 10.05
A11: Seat | B11: 220
A12: wash | B12: 16
A13: Mirror | B13: 27.59
A14: Indicator | B14: 15.24
A15: Fuel | B15: 10.42

Sheet Mazda CX3 AY17 YWX
A1: Item | B1: Amount | D1: Total Cost | E1: =SUM(B$2:B$1048576) -> 6409.99
A2: Price | B2: 5950 | D2: Sold For
A3: Fees | B3: 406.8 | D3: Profit / Loss | E3: =E2-E1 -> -6409.99
A4: Fuel | B4: 50.1
A5: Key Battery | B5: 3.09

Sheet Mazda 3 FY67 WDE
A1: Item | B1: Amount | D1: Total Cost | E1: =SUM(B$2:B$1048576) -> 6701.75
A2: Price | B2: 5850 | D2: Sold For
A3: Fees | B3: 406.8 | D3: Profit / Loss | E3: =E2-E1 -> -6701.75
A4: Fuel | B4: 15
A5: Bodywork | B5: 400
A6: fuel | B6: 21.95
A7: wash | B7: 8

Sheet CLA 200 WU66 MJX
A1: Item | B1: Amount | D1: Total Cost | E1: =SUM(B$2:B$1048576) -> 8558.78
A2: Price | B2: 8000 | D2: Sold For | E2: 12075
A3: Fees | B3: 442.8 | D3: Profit / Loss | E3: =E2-E1 -> 3516.22
A4: Wash | B4: 8
A5: Fuel | B5: 9.68
A6: MOT | B6: 40
A7: warranty | B7: 58.3

Sheet BMW 330E RX67 WPN
A1: Item | B1: Amount | D1: Total Cost | E1: =SUM(B$2:B$1048576) -> 8246.7
A2: Price | B2: 7725 | D2: Sold For | E2: =E1 -> 8246.7
A3: Fees | B3: 406.8 | D3: Profit / Loss | E3: =E2-E1 -> 0
A4: Fuek | B4: 6.17
A5: Wash | B5: 16
A6: Warranty | B6: 77.72
A7: Fuel | B7: 15.01

Sheet CLA 220 KU67 PWY
A1: Item | B1: Amount | D1: Total Cost | E1: =SUM(B$2:B$1048576) -> 7944.275
A2: Price | B2: 7300 | D2: Sold For | E2: 10250
A3: Fees | B3: 406.8 | D3: Profit / Loss | E3: =E2-E1 -> 2305.725
A4: Fuel | B4: =65.01/2 -> 32.505
A5: Fuel | B5: 9.8
A6: Alloy | B6: 80 | D6: =B4+B5+B10 -> 51.175
A7: Wash | B7: 8
A8: MOT | B8: 40
A9: Warranty | B9: 58.3
A10: Fuel | B10: 8.87

Sheet Audi A4 BG63 VYM
A1: Item | B1: Amount | D1: Total Cost | E1: =SUM(B$2:B$1048576) -> 5095.16
A2: Price | B2: 4800 | D2: Sold For
A3: MOT | B3: 40 | D3: Profit / Loss | E3: =E2-E1 -> -5095.16
A4: Fuel | B4: 20.01
A5: Wash | B5: 16
A6: Bodywork | B6: 150
A7: Alloys | B7: 60
A8: FUEL | B8: 9.15

Sheet 520D CF15 OWA
A1: Item | B1: Amount | D1: Total Cost | E1: =SUM(B$2:B$1048576) -> 6002.8
A2: Price | B2: 5300 | D2: Sold For
A3: Fees | B3: 382.8 | D3: Profit / Loss | E3: =E2-E1 -> -6002.8
A4: Charlie | B4: =100+120+80 -> 300
A5: Headlight fix | B5: 20

Sheet 520D YK66 DWU
A1: Item | B1: Amount | D1: Total Cost | E1: =SUM(B$2:B$1048576) -> 7952.26
A2: Price | B2: 7100 | D2: Sold For
A3: Fees | B3: 406.8 | D3: Profit / Loss | E3: =E2-E1 -> -7952.26
A4: Air | B4: 1.5
A5: Light | B5: 71.5
A6: Centre Vent | B6: 9.81
A7: Wash | B7: 15
A8: Oil | B8: 22.65
A9: Service | B9: 60
A10: Bodywork | B10: 250
A11: fuel | B11: 15

Sheet Mazda CX5 EJ14 PTX
A1: Item | B1: Amount | D1: Total Cost | E1: =SUM(B:B) -> 5336.28
A2: Price | B2: 4500 | D2: Sold For | E2: 7200
A3: Fees | B3: 406.8 | D3: Profit / Loss | E3: =E2-E1 -> 1863.72
A4: Rear Light | B4: 32
A5: Wash | B5: 16
A6: Fuel | B6: =41.56/2 -> 20.78
A7: Bodywork | B7: 250
A8: Fuel | B8: 10.13
A9: Wiper | B9: 12.99
A10: Fuel | B10: 9.86
A11: Warranty | B11: 77.72

Sheet 520D SA14 SYO
A1: Item | B1: Amount | D1: Total Cost | E1: =SUM(B$2:B$1048576) -> 3385.53
A2: PX | B2: 3093.24 | D2: Sold For | E2: 7989.29
A3: Detailer | B3: 30 | D3: Profit / Loss | E3: =E2-E1 -> 4603.76
A4: Alloys | B4: 60
A5: Wash | B5: 8
A6: Warranty | B6: 194.29

Sheet Q5 KM62 XFN
A1: Item | B1: Amount | D1: Total Cost | E1: =SUM(B:B) -> 6605.9
A2: Price | B2: 6000 | D2: Sold For
A3: Fees | B3: 346.8 | D3: Profit / Loss | E3: =E2-E1 -> -6605.9
A4: Toll | B4: 11.4
A5: Fuel | B5: 91.18
A6: Electrician | B6: 90
A7: Wash | B7: 16
A8: Sun visoe | B8: 2.38
A9: cig port | B9: 40
A10: Fuel | B10: 8.14

Sheet Merc C200 HF64 PLZ
A1: Item | B1: Amount | D1: Total Cost | E1: =SUM(B:B) -> 7089.8
A2: Price | B2: 6425 | D2: Sold For
A3: Fees | B3: 406.8 | D3: Profit / Loss | E3: =E2-E1 -> -7089.8
A4: Fuel | B4: 50
A5: SEAT REPAIR | B5: 200
A6: Wash | B6: 8

Sheet A5 LJ13 UAC
A1: Item | B1: Amount | D1: Total Cost | E1: =SUM(B:B) -> 4625.13
A2: Price | B2: 4100 | D2: Sold For | E2: 7250
A3: Fees | B3: 322.8 | D3: Profit / Loss | E3: =E2-E1 -> 2624.87
A4: Wash | B4: 16
A5: Fuel | B5: 8
A6: Fuel | B6: 8.1
A7: MOT | B7: 40
A8: Polish | B8: 30
A9: ULEZ | B9: 12.5
A10: warranty | B10: 77.72
A11: Fuel | B11: 10.01

Sheet Golf R VX16 XJU
A1: Item | B1: Amount | D1: Total Cost | E1: =SUM(B:B) -> 7491.5
A2: Price | B2: 7000 | D2: Sold For | E2: 9971
A3: Fees | B3: 346.8 | D3: Profit / Loss | E3: =E2-E1 -> 2479.5
A4: wash | B4: 16
A5: MOT | B5: 40
A6: Warranty | B6: 77.72
A7: Fuel | B7: 10.98

Sheet Passat PL18 KLM
A1: Item | B1: Amount | D1: Total Cost | E1: =SUM(B:B) -> 8516.69
A2: Price | B2: 7900 | D2: Sold For
A3: Boot latch | B3: 18.69 | D3: Profit / Loss | E3: =E2-E1 -> -8516.69
A4: tyres | B4: 100
A5: Fuel | B5: 5
A6: Seat repair | B6: 140
A7: Windscreen | B7: 220
A8: Boot fix | B8: 20
A9: Roof | B9: 100
A10: Roof handle | B10: 13

Sheet A6 DN14 WEP
A1: Item | B1: Amount | D1: Total Cost | E1: =SUM(B:B) -> 4606.41
A2: Price | B2: 4000 | D2: Sold For | E2: 7495
A3: Fees | B3: 322.8 | D3: Profit / Loss | E3: =E2-E1 -> 2888.59
A4: Fuel | B4: =39.78/2 -> 19.89
A5: Fuel | B5: 10
A6: Wash | B6: 16
A7: Oil leak | B7: 160
A8: Warranty | B8: 77.72

Sheet C Class BJ64 OSE
A1: Item | B1: Amount | D1: Total Cost | E1: =SUM(B:B) -> 7508.91
A2: Price | B2: 6300 | D2: Sold For | E2: 10800
A3: Fees | B3: 346.8 | D3: Profit / Loss | E3: =E2-E1 -> 3291.09
A4: Fuel | B4: =39.78/2 -> 19.89
A5: Fuel | B5: 40.3
A6: OSE Centre console | B6: 25.2
A7: Seat repair | B7: 220
A8: Tyres | B8: 220
A9: Map SD | B9: 22.99
A10: wash | B10: 8
A11: wash | B11: 8
A12: Tyre | B12: 55
A13: Fuel | B13: 15.01
A14: Wash | B14: 25
A15: Warranty | B15: 77.72
A16: Charlie | B16: 125

Sheet Mazda 6 WA13XCV
A1: Item | B1: Amount | D1: Total Cost | E1: =SUM(B:B) -> 5558.93
A2: Price | B2: 4400 | D2: Sold For
A3: Fees | B3: 406.8 | D3: Profit / Loss | E3: =E2-E1 -> -5558.93
A4: Fuel | B4: 35.05
A5: Headlight | B5: 74.95
A6: Grill | B6: 49.88
A7: Bodywork | B7: 300
A8: Alloys | B8: 240
A9: MOT | B9: 40
A10: Fuel | B10: 12.25

Sheet POLO GTI BK61 SWZ
A1: Item | B1: Amount | D1: Total Cost | E1: =SUM(B:B) -> 4779.49
A2: Price | B2: 4150 | D2: Sold For
A3: Fees | B3: 322.8 | D3: Profit / Loss | E3: =E2-E1 -> -4779.49
A4: Fuel | B4: =47.5+15.27 -> 62.77
A5: Carplay | B5: 52.28
A6: Uber | B6: =69.46/2 -> 34.73
A7: Bus | B7: =35.5/2 -> 17.75
A8: mirror switch | B8: 10.97
A9: fuel | B9: 8.19
A10: Electrician | B10: 120
C12: `

Sheet GOLF RJ14 YZN
A1: Item | B1: Amount | D1: Total Cost | E1: =SUM(B:B) -> 6993.22
A2: Price | B2: 6400 | D2: Sold For | E2: 8400
A3: Fees | B3: 406.8 | D3: Profit / Loss | E3: =E2-E1 -> 1406.78
A4: Fuel | B4: 5.17
A5: Fuel | B5: 64.58
A6: Uber | B6: =69.46/2 -> 34.73
A7: Bus | B7: =35.5/2 -> 17.75
A8: window button | B8: 5.89
A9: Warranty | B9: 58.3

Sheet CLA FV14 MYL
A1: Item | B1: Amount | D1: Total Cost | E1: =SUM(B:B) -> 8231.48
A2: Price | B2: 6700 | D2: Sold For | E2: 10995
A3: Fees | B3: 406.8 | D3: Profit / Loss | E3: =E2-E1 -> 2763.52
A4: Fuel | B4: 4.45
A5: Fuel | B5: 10.03
A6: Detailer | B6: 25
A7: Badges | B7: 11.44
A8: Alloys | B8: 160
A9: Wash | B9: 16
A10: Driver | B10: 30
A11: fuel | B11: 10.04
A12: Razak | B12: 650
A13: Tyres | B13: 90
A14: warranty | B14: 77.72
A15: MOT | B15: 40

Sheet Fiesta FN62HKO
A1: Item | B1: Amount | D1: Total Cost | E1: =SUM(B$2:B$1048576) -> 1459.24
A2: PX Value | B2: 1219.16 | D2: Sold For | E2: 5295
A3: Bodywork | B3: 40 | D3: Profit / Loss | E3: =E2-E1 -> 3835.76
A4: Detailer | B4: 35
A5: Battery | B5: 43.49
A6: Fuel | B6: 5
A7: Fuel | B7: 13.13
A8: fuel | B8: 5.16
A9: Warranty | B9: 58.3
A10: Kasim | B10: 40

Sheet Polo GTI VK62 THV
A1: Item | B1: Amount | D1: Total Cost | E1: =SUM(B:B) -> 5510.52
A2: Price | B2: 4900 | D2: Sold For | E2: 7795
A3: Fees | B3: 346.8 | D3: Profit / Loss | E3: =E2-E1 -> 2284.48
A4: wASH | B4: 15
A5: Oil Cap | B5: 4.73
A6: Bodywork | B6: 50
A7: fuel | B7: 14.28
A8: MOT | B8: 40
A9: Battery | B9: 61.99
A10: Warranty | B10: 77.72

Sheet Corsa YY65 CAU
A1: Item | B1: Amount | D1: Total Cost | E1: =SUM(B:B) -> 5238.035
A2: Price | B2: 4750 | D2: Sold For | E2: 6995
A3: Fees | B3: 346.8 | D3: Profit / Loss | E3: =E2-E1 -> 1756.965
A4: Wash | B4: 18
A5: Fuel | B5: 11.26
A6: Fuel | B6: 8.51
B7: =20.83/2 -> 10.415
A8: Fuel | B8: 5.05
A9: Tyre | B9: 48
A10: MOT | B10: 40

Sheet P2008 LS66 SVA
A1: Item | B1: Amount | D1: Total Cost | E1: =SUM(B:B) -> 6092.52
A2: Price | B2: 5500 | D2: Sold For
A3: Fees | B3: 406.8 | D3: Profit / Loss | E3: =E2-E1 -> -6092.52
B4: 8
A5: Fuel | B5: 25.02
A6: Fuel | B6: 47.61
A7: Fuel | B7: 5.09
A8: Charlie | B8: 100

Sheet BMW 318D S88 RDF
A1: Item | B1: Amount | D1: Total Cost | E1: =SUM(B:B) -> 6743.575
A2: Price | B2: 5700 | D2: Sold For
A3: Fees | B3: 406.8 | D3: Profit / Loss | E3: =E2-E1 -> -6743.575
B4: 5.13
B5: =20.83/2 -> 10.415
A6: Fuel | B6: 50.02
A7: charlie | B7: 100
A8: wash | B8: 16
A9: Bodywork | B9: 160
A10: Windscreen | B10: 280
A11: Fuel | B11: 15.21

Sheet P3008 MF15 OPJ
A1: Item | B1: Amount | D1: Total Cost | E1: =SUM(B:B) -> 4187.38
A2: Price | B2: 3500 | D2: Sold For | E2: 6394.29
A3: Fees | B3: 370.8 | D3: Profit / Loss | E3: =E2-E1 -> 2206.91
A4: Wash | B4: 14
A5: Spare typre | B5: 49.99
A6: Warranty | B6: 194.29
A7: ULEZ | B7: 12.5
A8: Fuel | B8: =41.56/2 -> 20.78
A9: Fuel | B9: 25.02

Sheet Audi A1 EN63 TKA 
A1: Item | B1: Amount | D1: Total Cost | E1: =SUM(B:B) -> 7672.2
A2: Price | B2: 6700 | D2: Sold For | E2: 9795
A3: Fees | B3: 346.8 | D3: Profit / Loss | E3: =E2-E1 -> 2122.8
A4: Fuel | B4: =25.02/2 -> 12.51
A5: Fuel | B5: 8.12
A6: Wash | B6: 18
A7: Fuel | B7: 8.04
A8: Warranty | B8: 52.45
A9: Charlie | B9: 120
A10: Comback | B10: 406.28

Sheet A5 WJ62 UVS
A1: Item | B1: Amount | D1: Total Cost | E1: =SUM(B:B) -> 5947.61
A2: Price | B2: 4925 | D2: Sold For | E2: 7995
A3: Fees | B3: 406.8 | D3: Profit / Loss | E3: =E2-E1 -> 2047.39
A4: Bodywork | B4: 250
A5: ULEZ | B5: 12.5
A6: Wash | B6: 16
A7: Tyres | B7: 250
A8: Fuel | B8: 9.59
A9: Warranty | B9: 77.72

Sheet Fabia GN66 YWZ PX
A1: Item | B1: Amount | D1: Total Cost | E1: =SUM(B$3:B$1048576) -> 122.46
A2: PX Value | B2: 4000 | D2: Sold For | E2: 6495
A3: Wash | B3: 8 | D3: Profit / Loss | E3: =E2-E1 -> 6372.54
A4: Door handle | B4: 19
A5: Fuel | B5: 8.28
A6: fuel | B6: 9.46
A7: warranty | B7: 77.72

Sheet Mokka LS13 UKA
A1: Item | B1: Amount | D1: Total Cost | E1: 551.27
A2: PX Value | B2: 1500 | D2: Sold For | E2: 2900
A3: Buttons | B3: 37.99 | D3: Profit | E3: =E2-E1 -> 2348.73
A4: Wash | B4: 10
A5: Bodywork | B5: 200
A6: Steering wheel cover | B6: 5.56
A7: Warranty | B7: 77.72
A8: Charlie | B8: 220
A9: Qashqai Recovery | B9: 230

Sheet BMW 328i YB61
A1: Item | B1: Amount | D1: Total Cost | E1: =SUM(B:B) -> 6686.68
A2: Car Price | B2: 3850 | D2: Sold For
A3: Fees | B3: 322.8 | D3: Profit / Loss | E3: =E2-E1 -> -6686.68
A4: Rasak | B4: 320
A5: fuel | B5: 5
A6: Bodywork | B6: 250
A7: fuel | B7: 9.96
A8: Alloys | B8: 240
A9: Wash | B9: 8
A10: fuel | B10: 4.99
A11: Air | B11: 1.5
A12: Steering wheel | B12: 151.2
A13: Investor Payout | B13: 623.23
B14: 900

Sheet Peugeot 2008 EU14
A1: Item | B1: Amount | D1: Total Cost | E1: =SUM(B:B) -> 1328.74
A2: Car Price | B2: 850 | D2: Sold For | E2: 2000
A3: Fees | B3: 370.8 | D3: Profit / Loss | E3: =E2-E1 -> 671.26
A4: Warranty | B4: 107.94 | C4: To be paid back

Sheet BMW 518D PG66
A1: Item | B1: Amount | D1: Total Cost | E1: =SUM(B:B) -> 6388.24
A2: Car Price | B2: 5300 | D2: Sold For
A3: Fees | B3: 406.8 | D3: Profit / Loss | E3: =E2-E1 -> -6388.24
A4: Fuel | B4: 25.01
A5: Train | B5: =(20.09+22.59)/2 -> 21.34
A6: Uber | B6: =7.9/2 -> 3.95
A7: Bus | B7: 5.55
A8: Bodywork | B8: 100
A9: Fuel | B9: 9.99
A10: Parking button | B10: 5.39
A11: Deep Wash | B11: 350
A12: fuel | B12: 10.27
A13: Parking Break | B13: 4.99
A14: Tyres | B14: 50
A15: Fuel | B15: 17.23
A16: Warranty | B16: 77.72

Sheet Ford Mondeo DG68
A1: Item | B1: Amount | D1: Total Cost | E1: =SUM(B:B) -> 6397.64
A2: Car Price | B2: 5500 | D2: Sold For | E2: 8795
A3: Fees | B3: 346.8 | D3: Profit / Loss | E3: =E2-E1 -> 2397.36 | F3: =E3*0.5+158 -> 1356.68
A4: Train | B4: =(20.09+22.59)/2 -> 21.34
A5: Uber | B5: =7.9/2 -> 3.95
A6: Bus | B6: 5.55
A7: MOT | B7: 40
A8: Electrician | B8: 135
A9: Charlie | B9: 180
A10: tyres | B10: 165
A11: Warranty

Sheet Smart Premium SR16 HKT
A1: Item | B1: Amount | D1: Total Cost | E1: =SUM(B:B) -> 5253.02
A2: Car Price | B2: 4600 | D2: Sold For | E2: 8995
A3: Fees | B3: 346.8 | D3: Profit / Loss | E3: =E2-E1 -> 3741.98
A4: Tyre (3) | B4: 115
A5: Fuel | B5: 36.1
A6: Fuel | B6: 29.4
A7: Wash | B7: 8
A8: MOT | B8: 40
A9: Warranty | B9: 77.72

Sheet BMW 120D PE65 LXZ
A1: Item | B1: Amount | D1: Total Cost | E1: =SUM(B:B) -> 6528.73
A2: Car Price | B2: 5665.88 | D2: Sold For
A3: Fees | B3: 394.8 | D3: Profit / Loss | E3: =E2-E1 -> -6528.73
A4: Bodywork | B4: 250
A5: Fuel | B5: 10
A6: MOT | B6: 40
A7: Tyre | B7: 140
A8: Wash | B8: 8
A9: Fuel | B9: 7.05
A10: Air | B10: 1.5
A11: Air | B11: 1.5
A12: Alloy | B12: 10 | C12: Cash

Sheet Suzuki Swift YB68 XYT
A1: Item | B1: Amount | D1: Total Cost | E1: =SUM(B:B) -> 5374.73
A2: Car Price | B2: 4950 | D2: Sold For
A3: Fees | B3: 346.8 | D3: Profit / Loss | E3: =E2-E1 -> -5374.73
A4: Fuel | B4: 19.93
A5: Wash | B5: 18
A6: Driver | B6: 40

Sheet Octavia VRS GY14 BZC
A1: Item | B1: Amount | D1: Total Cost | E1: =SUM(B:B) -> 8246.15
A2: Car Price | B2: 7023 | D2: Sold For
A3: Fees | B3: 430.8 | D3: Profit / Loss | E3: =E2-E1 -> -8246.15
A4: Bodywork | B4: 300
A5: Alloys | B5: 400
A6: Wash | B6: 12
A7: Fuel | B7: 10.4
A8: Warranty | B8: 69.95

Sheet BMW 520D EJ14
A1: Item | B1: Amount | D1: Total Cost | E1: =SUM(B:B) -> 6541.12
A2: Car Price | B2: 5650 | D2: Sold For | E2: 8495
A3: Driver Mirror | B3: 80 | D3: Profit / Loss | E3: =E2-E1 -> 1953.88
A4: Tyre | B4: 65
A5: Door trim | B5: 9.88
A6: Alloys | B6: 300
A7: Alloy caps | B7: 7.99
A8: cig cover | B8: 10.99
A9: Parking button | B9: 8.73
A10: Bodywork | B10: 300
A11: Rear vent | B11: 15.81
A12: Wash | B12: 15
A13: Warranty | B13: 77.72

Sheet Mitsubishi DN16 YXF
A1: Item | B1: Amount | D1: Total Cost | E1: =SUM(B:B) -> 6497.88
A2: Car Price | B2: 5200 | D2: Sold For | E2: 8650
A3: Fees | B3: 346.8 | D3: Profit / Loss | E3: =E2-E1 -> 2152.12
A4: Brake fluid | B4: 6
A5: Brake service | B5: 50
A6: Fuel | B6: 16.38
A7: Brake Pump | B7: 70
A8: Front bumper trim | B8: 25.99
A9: bodywork | B9: 150
A10: fuse box & relay | B10: 19.99
A11: diagnosis | B11: 125
A12: fuel | B12: 10
A13: Razak | B13: 400
A14: Warranty | B14: 77.72

Sheet Fiat 500 LK15
A1: Item | B1: Amount | D1: Total Cost | E1: =SUM(B:B) -> 4014.61
A2: Car Price | B2: 900 | D2: Sold For | E2: 6800
A3: Fees | B3: 322.8 | D3: Profit / Loss | E3: =E2-E1 -> 2785.39
A4: Recovery | B4: 120
A5: wash | B5: 8
A6: Fuel | B6: 5.75
A7: Gearbox | B7: 2500
A8: Warranty | B8: 77.72
A9: fuel | B9: 8.36
A10: Passanger handle | B10: 26.99
A11: cluster | B11: 44.99

Sheet Audi A3 LG61 RTV
A1: Item | B1: Amount | D1: Total Cost | E1: =SUM(B:B) -> 6493.7
A2: Car Price | B2: 5500 | D2: Sold For | E2: 8465
A3: Fees | B3: 346.8 | D3: Profit / Loss | E3: =E2-E1 -> 1971.3
A4: Jatin | B4: 50
A5: MOT | B5: 40
A6: Fuel | B6: 9.29
A7: Wash | B7: 15
A8: Fuel | B8: 9.22
A9: Fuel | B9: 3.44
A10: warranty | B10: 69.95
A11: Coolant leak | B11: 450

Sheet Audi A7 OV61 WKH
A1: Item | B1: Amount | D1: Total Cost | E1: =SUM(B:B) -> 7573.46
A2: Car Price | B2: 5000 | D2: Sold For
A3: Fees | B3: 382.5 | D3: Profit / Loss | E3: =E2-E1 -> -7573.46
A4: FUEL | B4: 51.48
A5: Train | B5: 38.11
A6: Uber | B6: =19.22/2 -> 9.61
A7: Coding | B7: 180
A8: MOT | B8: 40
A9: razak | B9: 720
A10: fuel | B10: 13.52
A11: Wash | B11: 12
A12: Fuel | B12: 15.39
A13: Charlie | B13: 700
A14: Radar | B14: 318 | H14: Delivery
A15: Grill | B15: 92.85 | G15: Fuel | H15: 8.89
G16: Fuel | H16: 45.19
G17: Fuel | H17: 70.04
G18: sum | H18: =SUM(H15:H17) -> 124.12

Sheet Fiat 500 LM64 FWU
A1: Item | B1: Amount | D1: Total Cost | E1: =SUM(B:B) -> 3730.74
A2: Car Price | B2: 3535 | D2: Sold For | E2: 5400
A3: Insurance | B3: 13.66 | D3: Profit / Loss | E3: =E2-E1 -> 1669.26
A4: Train | B4: 38.11
A5: Uber | B5: =19.22/2 -> 9.61
A6: Insurance | B6: 16.41
A7: Wash | B7: 8
A8: Mot | B8: 40
A9: Warranty | B9: 69.95

Sheet Polo GT CV65
A1: Item | B1: Amount | D1: Total Cost | E1: =SUM(B:B) -> 4528.8
A2: Car Price | B2: 4000 | D2: Sold For | E2: 6595
A3: Fees | B3: 358.8 | D3: Profit / Loss | E3: =E2-E1 -> 2066.2
A4: Fuel | B4: 24.43 | D4: Investor Profit | E4: =E3/2 -> 1033.1
A5: Insurance | B5: 14.32
A6: Train | B6: =26.6/2 -> 13.3
A7: Wage | B7: 40
A8: Wash | B8: 8
A9: Warranty | B9: 69.95

Sheet Nissan Note RV62 UMD
A1: Item | B1: Amount | D1: Total Cost | E1: =SUM(B:B) -> 2850.71
A2: Car Price | B2: 1200 | D2: Sold For | E2: 5375
A3: Fees | B3: =269*1.2 -> 322.8 | D3: Profit / Loss | E3: =E2-E1 -> 2524.29
A4: Insurance | B4: 30.51
A5: Fuel | B5: 24.77
A6: Uber | B6: 15.98
A7: Train | B7: =26.6/2 -> 13.3
A8: Wage | B8: 40
A9: Insurance | B9: 13.68
A10: Oil | B10: 20.95
A11: Bodywork | B11: 940
A12: Oil filter | B12: 5.88
A13: Radio | B13: 13.99
A14: Antenna | B14: 3.61
A15: Tape | B15: 3.09
A16: Fuel | B16: 5.31
A17: Note | B17: 120
A18: Fuel | B18: 6.89
A19: Warranty | B19: 69.95

Sheet BMW GT SV63 KKO
A1: Item | B1: Amount | D1: Total Cost | E1: =SUM(B:B) -> 6270.68 | G1: Delivery + Admin | H1: 599
A2: Car Price | B2: 5000 | D2: Sold For | E2: 8400 | G2: Fuel | H2: 77.21
A3: Fees | B3: =370.8+12 -> 382.8 | D3: Profit / Loss | E3: =E2-E1 -> 2129.32 | G3: Fuel | H3: 10.75
A4: Kasim | B4: 50 | G4: Toll | H4: 11.4
A5: Bodywork | B5: 120
A6: Insurance | B6: 36.22 | G6: SA Total | H6: =H1-SUM(H2:H4) -> 499.64
A7: Wash | B7: 10
A8: Fuel | B8: 10.31
A9: Warranty | B9: 86.35
A10: Comeback | B10: 575

Sheet BMW SX14 KKH
A1: Item | B1: Amount | D1: Total Cost | E1: =SUM(B:B) -> 6647.9
A2: Car Price | B2: 5750 | D2: Sold For | E2: 9050
A3: Fees | B3: 370.8 | D3: Profit / Loss | E3: =E2-E1 -> 2402.1
A4: Flight To Scotland | B4: 41.99 | E4: =E3/2 -> 1201.05
A5: Bus | B5: 7
A6: Insurance | B6: 39.21
A7: Fuel | B7: 66.33
A8: Insurance | B8: 27.76
A9: Toll road | B9: 10.5
A10: Alloys | B10: 220
A11: Wash | B11: 20
A12: fuel | B12: 6
A13: Fuel | B13: 10.59
A14: Warranty | B14: 77.72

Sheet Polo CY64 ACO
A1: Item | B1: Amount | D1: Total Cost | E1: =SUM(B:B) -> 4642.52
A2: Car price | B2: 4050 | D2: Sold For | E2: 5795
A3: Fees | B3: 346.8
A4: Wash | B4: 8 | D4: Profit / Loss | E4: =E2-E1 -> 1152.48
A5: Nasir | B5: 120
A6: MOT | B6: 40
A7: Warranty | B7: 77.72

Sheet Audi A3 HG08 EPZ
A1: Item | B1: Amount | D1: Total Cost | E1: 8
A2: Part Ex Value | B2: 800 | D2: Sold For | E2: 1995
A3: Wash | B3: 8 | D3: Profit / Loss | E3: 1586.99 | F3: Audi A4 Hamzi YB65 GRU Paid out - Profit factors SA paying Hamzi out of Pocket

Sheet Mazda 6
A1: Item | B1: Amount | D1: Total Cost | E1: =SUM(B:B) -> 4399.21
A2: Car Price | B2: 3900 | D2: Sold For | E2: 7250
A3: Fees | B3: 322.8 | D3: Profit / Loss | E3: =E2-E1 -> 2850.79
A4: oil | B4: 19.95
A5: Service | B5: 30
A6: Insurance | B6: 24.51
A7: Wash | B7: 20
A8: Wash | B8: 12
A9: Warranty | B9: 69.95

Sheet Honda CRV KU13 FBF
A1: Item | B1: Amount | D1: Total Cost | E1: =SUM(B:B) -> 5732.32
A2: Car Price | B2: 4650 | D2: Sold For | E2: 7995 | G2: ADMIN | H2: 99
A3: Fees | B3: 370.8 | D3: Profit / Loss | E3: =E2-E1 -> 2262.68 | G3: Delivery | H3: 120
A4: Fuel | B4: 30.01
A5: driver | B5: 50
A6: train | B6: 66.45
A7: uber | B7: 7.5
A8: Bodywork | B8: 130
A9: Insurance | B9: 29.14
A10: Wash | B10: 20
A11: Insurance | B11: 22.93
A12: Bodywork | B12: 200
A13: Wash | B13: 20
A14: Tyre Pump | B14: 3
A15: Wash | B15: 20
... A21: ulez | B21: 12.5

Sheet Audi A4 YB15GRU
A1: Item | B1: Amount | D1: Total Cost | E1: =SUM(B:B) -> 5975.85
A2: Car Price | B2: 5800 | D2: Sold For | E2: 7400 | G2: Part Ex Value | H2: 800
A3: Train | B3: 53.83 | D3: Profit / Loss | E3: =E2-E1 -> 1424.15
A4: Recovery of Vehicle | B4: =2.97 + 26.67 -> 29.64
A5: Fuel | B5: 40
A6: wash | B6: 20
A7: warranty | B7: 32.38

Sheet Polo MF14 TUH
A1: Item | B1: Amount | D1: Total Cost | E1: =SUM(B:B) -> 4901.89
A2: Car Price | B2: 3200 | D2: Sold For | E2: 5695
A3: fee | B3: 358.8 | D3: Profit / Loss | E3: =E2-E1 -> 793.11
A4: fuel | B4: 34.45
A5: uber | B5: 7.5
A6: driver | B6: 50
A7: train | B7: 66.45
A8: Charlie | B8: 465
A9: Electrician | B9: 320
A10: Bodywork | B10: 150
A11: Battery | B11: 43.24
A12: Wash | B12: 8
A13: Fuel | B13: 5.01
A14: Aux belt | B14: 25.84
A15: Belt change | B15: 10
B16: 77.72
B17: 20
A18: fuel | B18: 14.5
A19: fuel | B19: 5.38
A20: Driver drop off | B20: 40

Sheet Jaguar XF OY61 UTH
A1: Item | B1: Amount | D1: Total Cost | E1: =SUM(B:B) -> 3526.9367
A2: Car Price | B2: 2625 | D2: Sold For | E2: 5000
A3: Fees | B3: 358.8
A4: Train | B4: 53.83 | D4: Profit / Loss | E4: =E2-E1 -> 1473.0633
A5: Uber | B5: 2.97
A6: Insurance | B6: 40.07
A7: Insurance | B7: 101.77
A8: Fuel | B8: 19.84
A9: tires | B9: 90
A10: kassim | B10: =80/3 -> 26.666667
A11: Nasir | B11: 120
A12: Fuel | B12: 8
A13: Fuel | B13: 10.04
A14: Warranty | B14: 69.95

Sheet Peugot 107 LN11 
A1: Item | B1: Amount | D1: Total Cost | E1: =SUM(B:B) -> 2571.2167
A2: Car Price | B2: 2100 | D2: Sold For | E2: 3500
A3: Carwow | B3: 322.8 | D3: Profit / Loss | E3: =E2-E1 -> 928.78333
A4: Train | B4: 53.83
A5: Uber | B5: 2.97
A6: Wash | B6: 8
A7: fuel | B7: 46.95
A8: wash | B8: 10
A9: kassim | B9: =80/3 -> 26.666667

Sheet Polo BlueGT CE65 MJJ
A1: Item | B1: Amount | D1: Total Cost | E1: =SUM(B:B) -> 4783.32
A2: Car Price | B2: 4000 | D2: Sold For | E2: 6995
A3: Fuel | B3: 14.65 | D3: Profit / Loss | E3: =E2-E1 -> 2211.68
A4: Jatin | B4: 30
A5: wash | B5: 30
A6: Fuel | B6: 5.75
A7: Fuel | B7: 5.19
A8: Saleh | B8: 230
A9: Plate | B9: 15
A10: Fees | B10: 346.8
A11: Battery | B11: 4.58
A12: Plate | B12: 15
A13: Warranty | B13: 86.35

Sheet Golf Match LR15 EUT
A1: Item | B1: Amount | D1: Total Cost | E1: =SUM(B:B) -> 5248.4033
A2: Car Price | B2: 4750 | D2: Sold For | E2: 7495
A3: Carwow | B3: 370.8 | D3: Profit / Loss | E3: =E2-E1 -> 2246.5967
A4: Travel | B4: 74.63
A5: Driver | B5: 26.66
A6: Wash | B6: 15
A7: wash | B7: 8
A8: Uber | B8: =9.94/3 -> 3.3133333

Sheet Kuga VX15 DYU
A1: Item | B1: Amount | D1: Total Cost (£) | E1: =SUM(B:B) -> 5602.5433
A2: Price | B2: 4000 | D2: Sold For (£) | E2: 7793.28
A3: Fees | B3: 370.8 | D3: Profit / Loss (£) | E3: =E2-E1 -> 2190.7367
A4: Fuel | B4: 55.09
A5: Travel | B5: 74.63
A6: Driver | B6: 26.66
A7: Body work | B7: 600
A8: Fuel | B8: 12.19
A9: fuel | B9: 24.08
A10: wash | B10: 10
A11: Uber | B11: =9.94/3 -> 3.3133333
A12: gearbox service | B12: 130
A13: wash | B13: 12
A14: bATTERY | B14: 130.99
A15: cHANGE BATTERY | B15: 20
A16: FUEL | B16: 15.07
A17: Warranty | B17: 77.72
A18: Insurance | B18: 40

Sheet Fiat 500 CX14 PVO
A1: Item | B1: Amount | D1: Total Cost (£) | E1: =SUM(B2:B17) -> 4818.1433
A2: Price | B2: 4000 | D2: Sold For (£) | E2: 5995
A3: Fees | B3: 346.8 | D3: Profit / Loss (£) | E3: =E2-E1 -> 1176.8567
A4: Fuel | B4: 41.9
A5: Travel | B5: 74.63
A6: Driver | B6: 26.66
A7: Insurance | B7: 23.06
A8: Insurance | B8: 17.66
A9: MOT | B9: 40
A10: Uber | B10: =9.94/3 -> 3.3133333
A11: windscreen | B11: 160
A12: Warranty | B12: 69.95
A13: Insurance | B13: 14.17

Sheet Fiat 500 YB65 XPP
A1: Item | B1: Amount | D1: Total Cost | E1: =SUM(B:B) -> 4279.18
A2: Price | B2: 3500 | D2: Sold For | E2: 5450
A3: Fees | B3: 322.8 | D3: Profit / Loss | E3: =E2-E1 -> 1170.82
A4: Insurance | B4: 15.02
A5: Body work | B5: 150
A6: Jatin | B6: 40
A7: fuel | B7: 18.42
A8: BEN | B8: 20
A9: wash | B9: 8
A10: Door Handle | B10: 9.45
A11: Door Handle | B11: 18.55
A12: Warranty | B12: 69.95
A13: Door Handle | B13: 44.99
A14: Alloy refurb | B14: 55
A15: wash | B15: 7

Sheet Audi S5 SP08 KLX 
A1: Item | B1: Amount | D1: Total Cost (£) | E1: =SUM(B:B) -> 5494.46
A2: Price | B2: =4350 -> 4350 | D2: Sold For (£) | E2: 8995
A3: Fees | B3: 346.8 | D3: Profit / Loss (£) | E3: =E2-E1 -> 3500.54
A4: Fuel | B4: 76.69
A5: Wash | B5: 5
A6: Bodywork | B6: 300
A7: service and leak | B7: 185
A8: Fuel | B8: 7.76
A9: Wash | B9: 20
A10: fuel | B10: 12
A11: wash | B11: 8
A12: wash | B12: 20
A13: Fuel | B13: 9.92
A14: Parking module | B14: 24.99
A15: Parking module TSP | B15: -297 | C15: Refunded
A16: Fuel | B16: 9.9
A17: Parking module | B17: 265.39
A18: Electrician | B18: 140
A19: Warranty
A20: Fuel | B20: 10.01

Sheet Audi A5 ET65 BWO
A1: Item | B1: Amount | D1: Total Cost | E1: =SUM(B:B) -> 5437.63
A2: Car Price | B2: 4250 | D2: Sold For | E2: 8602
A3: Carwow | B3: 346.8 | D3: Profit / Loss | E3: =E2-E1 -> 3164.37
A4: Insurance | B4: 16.2
A5: Bodywork | B5: 760 | D5: Delivery
A6: Insurance | B6: 24.63 | D6: Fees | E6: 300
A7: MOT | B7: 40 | D7: Kasim | E7: 80
D8: Insurance | E8: 25.93
D9: Fuel | E9: 29.75
E12: =E6-E7-E8-E9 -> 164.32

Sheet Nissan Juke PK64 LRL
A1: Item | B1: Amount | D1: Total Cost | E1: =SUM(B:B) -> 3539.43
A2: Car Price | B2: 1500 | D2: Sold For
A3: Recovery | B3: 100 | D3: Profit / Loss | E3: =E2-E1 -> -3539.43
A4: Hpi Check | B4: 4.95
A5: Recovery | B5: 95
A6: Tyres | B6: 105
A7: Fuel | B7: 4.55
A8: Wash | B8: 18
A9: Autotrader | B9: 88.74
A10: Gearbox | B10: 1600
A11: Fuel | B11: 6.95
A12: Insurance | B12: 16.24

Sheet Fiat 500 WM63 XCE Grey
A1: Item | B1: Amount | D1: Total Cost | E1: =SUM(B:B) -> 2639.28
A2: Car Price | B2: 1400 | D2: Sold For | E2: 3595
A3: Carwow | B3: 274.8
A4: Fuel | B4: 9.91 | D4: Profit / Loss | E4: =E2-E1 -> 955.72
A5: Insurance | B5: 14.25
A6: Insurance | B6: 15.15
A7: Body work | B7: 600
A8: Brakes | B8: 200
A9: Insurance | B9: 17.5
A10: Door Handle | B10: 9.95
A11: Fuel | B11: 20
A12: Warranty | B12: 77.72

Sheet Nissan Micra NL55 YXG
A1: Item | B1: Amount | D1: Total Cost | E1: =SUM(B:B) -> 200
A2: PX value | B2: 200 | D2: Sold For | E2: 500
D4: Profit / Loss | E4: =E2-E1 -> 300

Sheet Polo HG57
A1: Item | B1: Amount | D1: Total Cost | E1: =SUM(B$3:B$1048576) -> 783.61
A2: Part ex | B2: 700 | D2: Sold For | E2: 2950
A3: Insurance | B3: 18.07 | D3: Profit / Loss | E3: =E2-E1 -> 2166.39
A4: Insurance | B4: 21.45
A5: Wash | B5: 15
A6: Insurance | B6: 19.89
A7: Spark Plugs | B7: 18.86
A8: Badge | B8: 7.3
A9: Body work | B9: 270
A10: Body work | B10: 400
A11: Wash | B11: 8
A12: Fuel | B12: 5.04

Sheet Volkswagen Polo JFZ 1824
A1: Item | B1: Amount | D1: Total Cost | E1: =SUM(B:B) -> 4895.8
A2: Car Price | B2: 4252.51 | D2: Sold For | E2: 7295
A3: Carwow | B3: 346.8 | D3: Profit / Loss | E3: =E2-E1 -> 2399.2
A4: Insurance | B4: 14.27 | D4: Investor Profit | E4: =E3/2 -> 1199.6
A5: Wash | B5: 30
A6: Insurance | B6: 18.3
A7: Ebay | B7: 21.79
A8: Handle | B8: 21.6
A9: Insurance | B9: 18.3
A10: Wash | B10: 15
A11: Fuel | B11: 7.28
A12: Warranty | B12: 69.95
A13: Autotrader | B13: 80

Sheet Smart Fortwo YT63 ENJ (B)
A1: Item | B1: Amount | D1: Total Cost | E1: =SUM(B:B) -> 2576
A2: Car Price | B2: 1500 | D2: Sold For | E2: 3900
A3: Carwow | B3: 274.8 | D3: Profit / Loss | E3: =E2-E1 -> 1324
A4: Bodywork | B4: 120
A5: Train | B5: 51.3
A6: Wages | B6: 53.3
A7: Insurance | B7: 20.52
A8: Fuel | B8: 20.01
A9: MOT | B9: 40
A10: Saleh | B10: 50
A11: Bodywork | B11: 120
A12: Insurance | B12: 18.6
A13: Insurance | B13: 15.24
A14: Insurance | B14: 15.88
A15: Insurance | B15: 15.85
A16: Seat Repair | B16: 100
A17: Auto Trader | B17: 70.74 | C17: £18 to be refunded
A18: Wash | B18: 25
A19: Warranty | B19: 64.76

Sheet Nissan Qashqai KM17 YTV
A1: Item | B1: Amount | D1: Total Cost | E1: =SUM(B:B) -> 8361.51 | G1: Part EX | H1: Mocha
A2: Car Price | B2: 4250 | D2: Sold For | E2: 8295 | G2: Value | H2: 1500
A3: Carwow | B3: 322.8 | D3: Profit / Loss | E3: =E2-E1 -> -66.51
A4: Recovery | B4: 400
A5: Train | B5: 17.2
A6: TFL | B6: 3.1
A7: Gearbox | B7: 3200
A8: MOT | B8: 40
A9: Insurance | B9: 21.98
A10: fuel | B10: 15.21
A11: wash | B11: 12
A12: Air | B12: 1.5
A13: Warranty | B13: 77.72

Sheet Audi A1 EJ11
A1: Item | B1: Amount | D1: Total Cost (£) | E1: =SUM(B:B) -> 5477.23
A2: Brought | B2: 5075 | D2: Sold For (£)
A3: Fees | B3: 346.8
A4: Cupholders | B4: 10.5 | D4: Profit / Loss (£)
A5: Fuel | B5: 14.93
A6: Wash | B6: 20
A7: Wash | B7: 10 | F7: FULL PAID James

Sheet Audi A1 MF12
A1: Item | B1: Amount | D1: Total Cost (£) | E1: =SUM(B:B) -> 4390.79
A2: Price | B2: 3500 | D2: Sold For (£) | E2: 7250
A3: Insurance | B3: 17.66 | D3: Profit / Loss (£) | E3: =E2-E1 -> 2859.21
A4: bodywork | B4: 640
A5: Driver | B5: 40 | F5: Delivery | G5: 70
A6: Wash | B6: 30 | F6: Fuel | G6: 9.12
A7: Insurance | B7: 17.12
A8: Sunvisor Clip | B8: 2.88 | G8: =G5-G6 -> 60.88
A9: Wash | B9: 8
A10: Wash | B10: 8
A11: Fuel | B11: 9.41
A12: MOT | B12: 40
A13: Warranty | B13: 77.72

Sheet Ford Fiesta EA65 NDL
A1: Item | B1: Amount | D1: Total Cost | E1: =SUM(B:B) -> 3556.61
A2: Car Price | B2: 2250 | C2: Investor James | D2: Sold For | E2: 3815
A3: Insurance | B3: 80.23 | D3: Profit / Loss | E3: =E2-E1 -> 258.39
A4: Petrol | B4: =15.49+8.53 -> 24.02
A5: Body Work | B5: 350 | C5: Investor James
A6: Reflectors | B6: 14.99
A7: Electrician | B7: 400 | C7: Investor James
A8: AutoTrader HPI | B8: 4.95
A9: Tyre Sensors | B9: 180 | C9: Investor James | E9: =SUM(B2,B5,B7,B9)+E3*0.4 -> 3283.356
A10: Auto Trader | B10: 70.74
A11: Petrol | B11: 15.07
A12: Insurance | B12: 17.12 | C12: Poppy
A13: Fuel | B13: 4.96
A14: Wash | B14: 10
A15: insurance | B15: 15.46
A16: fuel | B16: 5.07
A17: mot | B17: 40
A18: Spare tyre | B18: 50
A19: Fuel | B19: 4
A20: Battery | B20: 20

Sheet Nissan Navara WD63 NXU
A1: Item | B1: Amount | D1: Total Cost (£) | E1: =SUM(B:B) -> 6737.99
A2: Car Price | B2: 2000 | D2: Sold For (£) | E2: 9994
A3: Recovery | B3: 220 | D3: Profit / Loss (£) | E3: =E2-E1 -> 3256.01
A4: Petrol | B4: 30
A5: Battery | B5: 40
A6: Insurance | B6: 23.59
A7: Fuel Pump | B7: 479.94
A8: Redcorn | B8: 45
A9: Fuel | B9: 30 | C9: Mussey
A10: Fuel | B10: 21.97
A11: Recovery | B11: 150
A12: Mechanic | B12: 1700
A13: Insurance | B13: 26.31
A14: Wash | B14: 20
A15: Bodywork | B15: 800
A16: Insurance | B16: 24.79
A17: Windscreen | B17: 260
A18: Charlie | B18: 500
A19: Mirror | B19: 47
A20: MOT | B20: 40
A21: Wash | B21: 50
... A27: ULEZ | B27: 12.5

Sheet Ford Fiesta MK59 FUV
A1: Item | B1: Amount | D1: Total Cost | E1: =SUM(B:B) -> 3949.35
A2: Car Price | B2: 3100 | C2: Ebrahim | D2: Sold For | E2: 5795
A3: Carwow | B3: 322.8 | D3: Profit / Loss | E3: =E2-E1 -> 1845.65
A4: Train | B4: 33.3
A5: Fuel | B5: 36.61
A6: Tfl | B6: 3.8
A7: Charlie | B7: 228
A8: Badge | B8: 7.38
A9: wash | B9: 8 | C9: Poppy
A10: insurance | B10: 21.07
A11: Autotrader | B11: 88.74
A12: Super glue | B12: 7.59
A13: insurance | B13: 17.21
A14: Fuel | B14: 44.85
A15: jatin | B15: 30

Sheet Nissan Note HY10 RRO
A1: Item | B1: Amount | D1: Total Cost | E1: =SUM(B:B) -> 2243.33
A2: Car Price | B2: 1400 | D2: Sold For | E2: ='Stock Data'!L92 -> 2989.66
A3: Carwow | D3: Profit / Loss | E3: =E2-E1 -> 746.33
A4: Bodywork | B4: 250
A5: Impound | B5: 360
A6: Insurance | B6: 24.86
A7: Exhaust | B7: 75.66
A8: Insurance | B8: 16.17
A9: Fuel | B9: 7.26
A10: Insurance | B10: 24.1
A11: Wash | B11: 25
A12: Insurance | B12: 20.28
A13: MOT | B13: 40

Sheet Fiat 500 DP64CXV White
A1: Item | B1: Amount | D1: Total Cost | E1: =SUM(B:B) -> 2386.87
A2: Car Price | B2: 2000 | D2: Sold For | E2: 4695
A3: Fuel | B3: 15.08 | D3: Profit / Loss | E3: =E2-E1 -> 2308.13
A4: Insurance | B4: 21.43
A5: Injector Cleaner | B5: 6.99
A6: Fuel | B6: 10.02
A7: Wash | B7: 10
A8: AutoTrader | B8: 70.74
A9: Wash | B9: 25
A10: Insurance | B10: 15.71
A11: Warranty | B11: 69.95
A12: Door Handle | B12: 9.95
A13: Diagnosis Fee | B13: 132
